Workbook

Sheet READ ME
A1: Date | B1: 46082
A3: Description | B3: This file provides traceability from Business use case > workflow > task > user story & persona > description > acceptance criteria. It also contains functional requirements to enable the user stories
B4: the Plan_business_use_cases tab contains an export of the ADL JIRA advanced plan - relfecting the DLE Use Case taxonomy.
B5: the plan export does not contain details contained on the actual tickets
B6: the ERM project with Parent tab is an export of the ADL JIRA EDLM Requirements Management Project and contains key ticket details.
B7: The UseCase to Accept Criteria tab maps to 2 files together using Plan_business_use_cases: "Work item key" and ERM project with Parent "issue key"
B9: Many of these requirements can be visualized in the DLE Workflow UIUX PDFs.

Sheet Plan_business_use_cases
A1: Hierarchy | B1: Title | C1: Space | D1: Releases (roll-up) | E1: Releases | F1: Team (roll-up) | G1: Team | H1: Assignee | I1: Reporter | J1: Sprint (roll-up) | K1: Sprint | L1: Target start date | M1: Target end date | N1: Due date (roll-up) | O1: Due date | P1: Estimates (d) (roll-up) | Q1: Estimates (d) | R1: Parent | S1: Priority | T1: Labels | U1: Components | V1: Work item key | W1: Work item status | X1: Goal | Y1: Goal status | Z1: Idea | AA1: Progress (%) | AB1: Progress completed (d) | AC1: Progress remaining (d) | AD1: Progress (%) work item count (IC) | AE1: To do IC | AF1: In progress IC | AG1: Done IC | AH1: Total IC | AI1: Start date (roll-up) | AJ1: Start date | AK1: User Persona(s)
A2: Use Case | B2: Configure: DLE System Management | C2: DLE - Top Level Planning | F2: ADL Human Centered Design [EXT] | G2: ADL Human Centered Design [EXT] | I2: Hunter Smith | J2: EDLM Sprint 47, EDLM Sprint 48 | N2: 45910 | S2: Medium | V2: DTLP-43 | W2: Backlog | AA2: 0 | AB2: 0 | AC2: 0 | AD2: 0 | AE2: 3 | AF2: 0 | AG2: 0 | AH2: 3 | AI2: 45882
A3: Initiative | B3: Install & Configure DLE Systems | C3: DLE - Top Level Planning | F3: ADL Human Centered Design [EXT] | G3: ADL Human Centered Design [EXT] | I3: Hunter Smith | J3: EDLM Sprint 47, EDLM Sprint 48 | N3: 45910 | R3: Configure: DLE System Management | S3: Medium | U3: EDLM Moodle LMS | V3: DTLP-44 | W3: Backlog | AA3: 0 | AB3: 0 | AC3: 0 | AD3: 0 | AE3: 6 | AF3: 0 | AG3: 0 | AH3: 6 | AI3: 45882
A4: Epic | B4: Provision Organizational Tenancies (Domains) | C4: EDLM - Requirements Management | G4: ADL Human Centered Design [EXT] | I4: Hunter Smith | R4: Install & Configure DLE Systems | S4: Medium | V4: ERM-2093 | W4: Backlog | AA4: 0 | AB4: 0 | AC4: 0 | AD4: 0 | AE4: 0 | AF4: 0 | AG4: 0 | AH4: 0
A5: Epic | B5: Install TLA Reference Implementation Components | C5: EDLM - Requirements Management | G5: ADL Human Centered Design [EXT] | I5: Hunter Smith | R5: Install & Configure DLE Systems | S5: Medium | V5: ERM-2094 | W5: Backlog | AA5: 0 | AB5: 0 | AC5: 0 | AD5: 0 | AE5: 0 | AF5: 0 | AG5: 0 | AH5: 0
A6: Epic | B6: Configure Software, Databases, and Services | C6: EDLM - Requirements Management | F6: ADL Human Centered Design [EXT] | G6: ADL Human Centered Design [EXT] | I6: Hunter Smith | R6: Install & Configure DLE Systems | S6: Medium | U6: EDLM Moodle LMS, EDLM Portal | V6: ERM-2095 | W6: Backlog | AA6: 0 | AB6: 0 | AC6: 0 | AD6: 33.33 | AE6: 4 | AF6: 0 | AG6: 2 | AH6: 6
A7: Story | B7: As an [Administrator], I want to import multiple P2881 profiles into the ECC data model | C7: EDLM - Requirements Management | G7: ADL Human Centered Design [EXT] | I7: Hunter Smith | R7: Configure Software, Databases, and Services | S7: Medium | U7: ecc/ecc-openlxp-xis | V7: ERM-2228 | W7: Backlog | AA7: 0 | AB7: 0 | AC7: 0 | AD7: 0 | AE7: 0 | AF7: 0 | AG7: 0 | AH7: 0 | AK7: EDLM Schema Administrator
A8: Story | B8: As an [Experience Manager], I want to preview and sync course catalog page layouts with the structure of ingested content profiles | C8: EDLM - Requirements Management | G8: ADL Human Centered Design [EXT] | I8: Hunter Smith | R8: Configure Software, Databases, and Services | S8: Medium | U8: ldss/openlxp-xms | V8: ERM-2229 | W8: Backlog | AA8: 0 | AB8: 0 | AC8: 0 | AD8: 0 | AE8: 0 | AF8: 0 | AG8: 0 | AH8: 0 | AK8: EDLM Experience Manager
A9: Story | B9: As a [System Admin], I want access to help desk to customize the configuration of my DLE environment | C9: EDLM - Requirements Management | G9: ADL Human Centered Design [EXT] | I9: Ashley Howell | R9: Configure Software, Databases, and Services | S9: Medium | V9: ERM-147 | W9: Backlog | AA9: 0 | AB9: 0 | AC9: 0 | AD9: 0 | AE9: 0 | AF9: 0 | AG9: 0 | AH9: 0 | AK9: EDLM IT System Administrator
A10: Story | B10: As a [System Admin], I want to set up different course catalog spotlights for different DHRA customers within the EDLM Portal | C10: EDLM - Requirements Management | G10: ADL Human Centered Design [EXT] | R10: Configure Software, Databases, and Services | S10: Medium | U10: EDLM Portal | V10: ERM-2701 | W10: Backlog | AA10: 0 | AB10: 0 | AC10: 0 | AD10: 0 | AE10: 0 | AF10: 0 | AG10: 0 | AH10: 0
A11: Epic | B11: Set up identity and access management | C11: EDLM - Requirements Management | F11: ADL Human Centered Design [EXT] | G11: ADL Human Centered Design [EXT] | I11: Hunter Smith | J11: EDLM Sprint 47, EDLM Sprint 48 | N11: 45910 | R11: Install & Configure DLE Systems | S11: Medium | V11: ERM-2713 | W11: Backlog | AA11: 0 | AB11: 0 | AC11: 0 | AD11: 0 | AE11: 3 | AF11: 0 | AG11: 0 | AH11: 3 | AI11: 45882
A12: Story | B12: As a [Site Admin] I would like to be able to configure the ECCR utilize JWT for user auth | C12: EDLM - Requirements Management | G12: ADL Human Centered Design [EXT] | I12: Hunter Smith | K12: EDLM Sprint 48 [EXT] [COMPLETED] + EDLM Sprint 47 [EXT] [COMPLETED] | R12: Set up identity and access management | S12: Medium | U12: eccr/frontend, eccr/backend | V12: ERM-294 | W12: Backlog | AA12: 0 | AB12: 0 | AC12: 0 | AD12: 0 | AE12: 0 | AF12: 0 | AG12: 0 | AH12: 0 | AK12: EDLM IT System Administrator
A13: Story | B13: As a [Competency Manager], I want my credentials (e.g., name) to be populated when I log in so that I can easily confirm that I am accessing my account. | C13: EDLM - Requirements Management | G13: ADL Human Centered Design [EXT] | I13: Ashley Howell | R13: Set up identity and access management | S13: Medium | V13: ERM-350 | W13: Backlog | AA13: 0 | AB13: 0 | AC13: 0 | AD13: 0 | AE13: 0 | AF13: 0 | AG13: 0 | AH13: 0 | AK13: EDLM Competency Manager
A14: Story | B14: As a Competency Manager, I want my credentials (e.g., name) to be populated when I log in so that I can easily confirm that I am accessing my account. | C14: EDLM - Requirements Management | G14: ADL Human Centered Design [EXT] | R14: Set up identity and access management | S14: Medium | V14: ERM-1554 | W14: Backlog | AA14: 0 | AB14: 0 | AC14: 0 | AD14: 0 | AE14: 0 | AF14: 0 | AG14: 0 | AH14: 0
A15: Epic | B15: Integrate with existing DoD Infrastructure | C15: EDLM - Requirements Management | G15: ADL Human Centered Design [EXT] | I15: Hunter Smith | R15: Install & Configure DLE Systems | S15: Medium | U15: EDLM Portal | V15: ERM-2714 | W15: Backlog | AA15: 0 | AB15: 0 | AC15: 0 | AD15: 0 | AE15: 1 | AF15: 0 | AG15: 0 | AH15: 1 | AK15: EDLM IT System Admin
A16: Story | B16: As an [ADL Admin], I want to configure Zendesk so I can integrate the defined business rules and workflows | C16: EDLM - Requirements Management | H16: Desiree Esiere | R16: Integrate with existing DoD Infrastructure | S16: High | T16: Zendesk_DANTES | U16: EDLM Portal | V16: ERM-2832 | W16: Backlog | AA16: 0 | AB16: 0 | AC16: 0 | AD16: 0 | AE16: 0 | AF16: 0 | AG16: 0 | AH16: 0 | AK16: EDLM IT System Admin
A17: Epic | B17: Validate System Readiness | C17: EDLM - Requirements Management | G17: ADL Human Centered Design [EXT] | I17: Hunter Smith | R17: Install & Configure DLE Systems | S17: Medium | V17: ERM-2715 | W17: Backlog | AA17: 0 | AB17: 0 | AC17: 0 | AD17: 0 | AE17: 0 | AF17: 0 | AG17: 0 | AH17: 0
A18: Initiative | B18: Maintenance: Cybersecurity / Patches / Updates | C18: DLE - Top Level Planning | G18: ADL Human Centered Design [EXT] | I18: Hunter Smith | R18: Configure: DLE System Management | S18: Medium | V18: DTLP-45 | W18: Backlog | AA18: 0 | AB18: 0 | AC18: 0 | AD18: 0 | AE18: 0 | AF18: 0 | AG18: 0 | AH18: 0
A19: Initiative | B19: Help Desk & Support | C19: DLE - Top Level Planning | G19: ADL Human Centered Design [EXT] | I19: Hunter Smith | R19: Configure: DLE System Management | S19: Medium | V19: DTLP-46 | W19: Backlog | AA19: 0 | AB19: 0 | AC19: 0 | AD19: 0 | AE19: 0 | AF19: 0 | AG19: 0 | AH19: 0
A20: Use Case | B20: Configure: TLA Data Management | C20: DLE - Top Level Planning | F20: ADL RD&E [EXT], ADL Human Centered Design [EXT], Deloitte [EXT] | G20: ADL Human Centered Design [EXT] | I20: Hunter Smith | S20: Medium | V20: DTLP-38 | W20: Backlog | AA20: 0 | AB20: 0 | AC20: 0 | AD20: 0 | AE20: 4 | AF20: 0 | AG20: 0 | AH20: 4
A21: Initiative | B21: Manage a Language Set | C21: DLE - Top Level Planning | F21: ADL RD&E [EXT], ADL Human Centered Design [EXT], Deloitte [EXT] | G21: ADL Human Centered Design [EXT] | I21: Hunter Smith | R21: Configure: TLA Data Management | S21: Medium | U21: EDLM LDSS | V21: DTLP-39 | W21: Backlog | AA21: 0 | AB21: 0 | AC21: 0 | AD21: 0 | AE21: 4 | AF21: 0 | AG21: 0 | AH21: 4
A22: Epic | B22: [LDSS] Configure Language Set | C22: EDLM - Requirements Management | I22: Hunter Smith | R22: Manage a Language Set | S22: Medium | U22: EDLM LDSS | V22: ERM-2098 | W22: Backlog | AA22: 0 | AB22: 0 | AC22: 0 | AD22: 0 | AE22: 0 | AF22: 0 | AG22: 0 | AH22: 0
A23: Epic | B23: [LDSS] Create a Language Set | C23: EDLM - Requirements Management | F23: ADL RD&E [EXT], ADL Human Centered Design [EXT], Deloitte [EXT] | G23: ADL Human Centered Design [EXT] | H23: Andy Johnson | I23: Hunter Smith | R23: Manage a Language Set | S23: Medium | U23: EDLM LDSS, P2881 Learning Experience Metadata | V23: ERM-2099 | W23: Backlog | AA23: 0 | AB23: 0 | AC23: 0 | AD23: 9.09 | AE23: 20 | AF23: 0 | AG23: 2 | AH23: 22
A24: Story | B24: As a [Glossary Manager], when Indexing a LanguageSet, I would like to upload a LanguageSets file to index the terms and definitions it contains | C24: EDLM - Requirements Management | G24: ADL Human Centered Design [EXT] | I24: Hunter Smith | R24: [LDSS] Create a Language Set | S24: Medium | U24: EDLM LDSS, ldss/openlxp-xss, ldss-xss/CCV-LCV, ldss/openlxp-xss-ui | V24: ERM-462 | W24: Backlog | AA24: 0 | AB24: 0 | AC24: 0 | AD24: 0 | AE24: 0 | AF24: 0 | AG24: 0 | AH24: 0 | AK24: EDLM Glossary Manager
A25: Story | B25: As a [Glossary Manager] I would like to save my LanguageSet as a draft to resume later | C25: EDLM - Requirements Management | G25: ADL Human Centered Design [EXT] | I25: Hunter Smith | R25: [LDSS] Create a Language Set | S25: Medium | U25: EDLM LDSS, ldss/openlxp-xss, ldss-xss/CCV-LCV, ldss/openlxp-xss-ui | V25: ERM-514 | W25: Backlog | AA25: 0 | AB25: 0 | AC25: 0 | AD25: 0 | AE25: 0 | AF25: 0 | AG25: 0 | AH25: 0 | AK25: EDLM Glossary Manager
A26: Story | B26: As a [Glossary Manager] I would like to fully define term definitions | C26: EDLM - Requirements Management | G26: ADL Human Centered Design [EXT] | I26: Florian Tolk | R26: [LDSS] Create a Language Set | S26: Medium | U26: EDLM LDSS, ldss/openlxp-xss, ldss-xss/CCV-LCV, ldss/openlxp-xss-ui | V26: ERM-470 | W26: Backlog | AA26: 0 | AB26: 0 | AC26: 0 | AD26: 0 | AE26: 0 | AF26: 0 | AG26: 0 | AH26: 0 | AK26: EDLM Glossary Manager
A27: Story | B27: As a [Glossary Manager], when Registering Terms, I would like the ability to input a definition for a Term (CCVID) | C27: EDLM - Requirements Management | G27: ADL Human Centered Design [EXT] | I27: Hunter Smith | R27: [LDSS] Create a Language Set | S27: Medium | U27: EDLM LDSS, ldss/openlxp-xss, ldss-xss/CCV-LCV, ldss/openlxp-xss-ui | V27: ERM-497 | W27: Backlog | AA27: 0 | AB27: 0 | AC27: 0 | AD27: 0 | AE27: 0 | AF27: 0 | AG27: 0 | AH27: 0 | AK27: EDLM Glossary Manager
A28: Story | B28: As a [Glossary Manager], when Registering Terms, i would like to capture Context, Context Description, and Labels for a Term (CCVID) | C28: EDLM - Requirements Management | G28: ADL Human Centered Design [EXT] | I28: Hunter Smith | R28: [LDSS] Create a Language Set | S28: Medium | U28: EDLM LDSS, ldss/openlxp-xss, ldss-xss/CCV-LCV, ldss/openlxp-xss-ui | V28: ERM-1033 | W28: Backlog | AA28: 0 | AB28: 0 | AC28: 0 | AD28: 0 | AE28: 0 | AF28: 0 | AG28: 0 | AH28: 0 | AK28: EDLM Glossary Manager
A29: Story | B29: As a [Glossary Manager] when Registering Terms, I would like there to be a deconfliction service that notifies me if my desired definition already exists and point me to the correct term within that language set | C29: EDLM - Requirements Management | G29: ADL Human Centered Design [EXT] | I29: Hunter Smith | R29: [LDSS] Create a Language Set | S29: Medium | U29: EDLM LDSS, ldss/openlxp-xss, ldss-xss/CCV-LCV, ldss/openlxp-xss-ui | V29: ERM-498 | W29: Backlog | AA29: 0 | AB29: 0 | AC29: 0 | AD29: 0 | AE29: 0 | AF29: 0 | AG29: 0 | AH29: 0 | AK29: EDLM Glossary Manager
A30: Story | B30: As a [Glossary Manager] I would like to recieve a notification when a definition for a term with a similar context already exists within the uploaded languageSet | C30: EDLM - Requirements Management | G30: ADL Human Centered Design [EXT] | I30: Hunter Smith | R30: [LDSS] Create a Language Set | S30: Medium | U30: EDLM LDSS, ldss/openlxp-xss, ldss-xss/CCV-LCV, ldss/openlxp-xss-ui | V30: ERM-515 | W30: Backlog | AA30: 0 | AB30: 0 | AC30: 0 | AD30: 0 | AE30: 0 | AF30: 0 | AG30: 0 | AH30: 0 | AK30: EDLM Glossary Manager
A31: Story | B31: As a [Glossary Manager], I want to drag and drop a file to upload a language set | C31: EDLM - Requirements Management | G31: ADL Human Centered Design [EXT] | I31: Ashley Howell | R31: [LDSS] Create a Language Set | S31: Medium | U31: EDLM LDSS, ldss/openlxp-xss, ldss-xss/CCV-LCV, ldss/openlxp-xss-ui | V31: ERM-1000 | W31: Backlog | AA31: 0 | AB31: 0 | AC31: 0 | AD31: 0 | AE31: 0 | AF31: 0 | AG31: 0 | AH31: 0 | AK31: EDLM Glossary Manager
A32: Story | B32: As a [Glossary Manager], I want to preview the language file that I uploaded so I can ensure I am uploading the correct language set | C32: EDLM - Requirements Management | G32: ADL Human Centered Design [EXT] | I32: Ashley Howell | R32: [LDSS] Create a Language Set | S32: Medium | U32: EDLM LDSS, ldss/openlxp-xss, ldss-xss/CCV-LCV, ldss/openlxp-xss-ui | V32: ERM-1001 | W32: Backlog | AA32: 0 | AB32: 0 | AC32: 0 | AD32: 0 | AE32: 0 | AF32: 0 | AG32: 0 | AH32: 0 | AK32: EDLM Glossary Manager
A33: Story | B33: As a [Glossary Manager], I want to see the different terms and definitions that are aligned to terms within my language set | C33: EDLM - Requirements Management | G33: ADL Human Centered Design [EXT] | I33: Ashley Howell | R33: [LDSS] Create a Language Set | S33: Medium | U33: EDLM LDSS, ldss/openlxp-xss, ldss-xss/CCV-LCV, ldss/openlxp-xss-ui | V33: ERM-1002 | W33: Backlog | AA33: 0 | AB33: 0 | AC33: 0 | AD33: 0 | AE33: 0 | AF33: 0 | AG33: 0 | AH33: 0 | AK33: EDLM Glossary Manager
A34: Story | B34: As a [Glossary Manager], I want to see the alignment percentage for a term and definition that is aligned to terms within my language set | C34: EDLM - Requirements Management | G34: ADL Human Centered Design [EXT] | I34: Ashley Howell | R34: [LDSS] Create a Language Set | S34: Low | U34: EDLM LDSS, ldss/openlxp-xss, ldss-xss/CCV-LCV, ldss/openlxp-xss-ui | V34: ERM-1003 | W34: Backlog | AA34: 0 | AB34: 0 | AC34: 0 | AD34: 0 | AE34: 0 | AF34: 0 | AG34: 0 | AH34: 0 | AK34: EDLM Glossary Manager
A35: Story | B35: As a [Glossary Manager], I want to select a term's definition that I want to use and add a tag to it for my term within a language set | C35: EDLM - Requirements Management | G35: ADL Human Centered Design [EXT] | I35: Ashley Howell | R35: [LDSS] Create a Language Set | S35: Medium | U35: EDLM LDSS, ldss/openlxp-xss, ldss-xss/CCV-LCV, ldss/openlxp-xss-ui | V35: ERM-1004 | W35: Backlog | AA35: 0 | AB35: 0 | AC35: 0 | AD35: 0 | AE35: 0 | AF35: 0 | AG35: 0 | AH35: 0 | AK35: EDLM Glossary Manager
A36: Epic | B36: [LDSS] Edit a Language Set | C36: EDLM - Requirements Management | F36: ADL Human Centered Design [EXT] | G36: ADL Human Centered Design [EXT] | I36: Hunter Smith | R36: Manage a Language Set | S36: Medium | U36: EDLM LDSS | V36: ERM-2100 | W36: Backlog | AA36: 0 | AB36: 0 | AC36: 0 | AD36: 0 | AE36: 11 | AF36: 0 | AG36: 0 | AH36: 11
A37: Story | B37: As a [Glossary Manager], I want to see all of my language sets so I can view them in one place | C37: EDLM - Requirements Management | G37: ADL Human Centered Design [EXT] | I37: Ashley Howell | R37: [LDSS] Edit a Language Set | S37: High | U37: EDLM LDSS, ldss/openlxp-xss, ldss-xss/CCV-LCV | V37: ERM-997 | W37: Backlog | AA37: 0 | AB37: 0 | AC37: 0 | AD37: 0 | AE37: 0 | AF37: 0 | AG37: 0 | AH37: 0 | AK37: EDLM Glossary Manager
A38: Story | B38: As a [Glossary Manager], I want to expand/collapse a selected language set so I can see all associated terms and relationships | C38: EDLM - Requirements Management | G38: ADL Human Centered Design [EXT] | I38: Ashley Howell | R38: [LDSS] Edit a Language Set | S38: Medium | U38: EDLM LDSS, ldss/openlxp-xss, ldss-xss/CCV-LCV | V38: ERM-998 | W38: Backlog | AA38: 0 | AB38: 0 | AC38: 0 | AD38: 0 | AE38: 0 | AF38: 0 | AG38: 0 | AH38: 0 | AK38: EDLM Glossary Manager
A39: Story | B39: As a [Glossary Manager], I would like to search for terms based on keywords within the definitions | C39: EDLM - Requirements Management | G39: ADL Human Centered Design [EXT] | I39: Hunter Smith | R39: [LDSS] Edit a Language Set | S39: Medium | U39: EDLM LDSS, ldss/openlxp-xss, ldss-xss/CCV-LCV | V39: ERM-528 | W39: Backlog | AA39: 0 | AB39: 0 | AC39: 0 | AD39: 0 | AE39: 0 | AF39: 0 | AG39: 0 | AH39: 0 | AK39: EDLM Glossary Manager
A40: Story | B40: As a [Glossary Manager], I would like to search for terms based on the UID, Context, and Context Description | C40: EDLM - Requirements Management | G40: ADL Human Centered Design [EXT] | I40: Hunter Smith | R40: [LDSS] Edit a Language Set | S40: Medium | U40: ldss/openlxp-xss, ldss-xss/CCV-LCV | V40: ERM-536 | W40: Backlog | AA40: 0 | AB40: 0 | AC40: 0 | AD40: 0 | AE40: 0 | AF40: 0 | AG40: 0 | AH40: 0 | AK40: EDLM Glossary Manager
A41: Story | B41: As a [Glossary Manager], I would like to see my search results display within a table with sortable columns | C41: EDLM - Requirements Management | G41: ADL Human Centered Design [EXT] | I41: Hunter Smith | R41: [LDSS] Edit a Language Set | S41: High | U41: EDLM LDSS, ldss/openlxp-xss, ldss-xss/CCV-LCV, ldss/openlxp-xss-ui | V41: ERM-538 | W41: Backlog | AA41: 0 | AB41: 0 | AC41: 0 | AD41: 0 | AE41: 0 | AF41: 0 | AG41: 0 | AH41: 0 | AK41: EDLM Glossary Manager
A42: Story | B42: As a [Glossary Manager], I would like to filter my search results based on fields in the table displayed | C42: EDLM - Requirements Management | G42: ADL Human Centered Design [EXT] | I42: Hunter Smith | R42: [LDSS] Edit a Language Set | S42: Low | U42: ldss/openlxp-xss, ldss-xss/CCV-LCV | V42: ERM-537 | W42: Backlog | AA42: 0 | AB42: 0 | AC42: 0 | AD42: 0 | AE42: 0 | AF42: 0 | AG42: 0 | AH42: 0 | AK42: EDLM Glossary Manager
A43: Story | B43: As a [Glossary Manager], when Indexing a LanguageSet, I would like the ability to register a new term to an existing languageSet | C43: EDLM - Requirements Management | G43: ADL Human Centered Design [EXT] | I43: Hunter Smith | R43: [LDSS] Edit a Language Set | S43: Medium | U43: ldss/openlxp-xss, ldss-xss/CCV-LCV | V43: ERM-496 | W43: Backlog | AA43: 0 | AB43: 0 | AC43: 0 | AD43: 0 | AE43: 0 | AF43: 0 | AG43: 0 | AH43: 0 | AK43: EDLM Glossary Manager
A44: Story | B44: As a [Glossary Manager], I would like the ability to edit an existing term in an existing Language Set | C44: EDLM - Requirements Management | G44: ADL Human Centered Design [EXT] | I44: Hunter Smith | R44: [LDSS] Edit a Language Set | S44: Medium | U44: ldss/openlxp-xss, ldss-xss/CCV-LCV | V44: ERM-535 | W44: Backlog | AA44: 0 | AB44: 0 | AC44: 0 | AD44: 0 | AE44: 0 | AF44: 0 | AG44: 0 | AH44: 0 | AK44: EDLM Glossary Manager
A45: Story | B45: As a [Glossary Manager], I would like to be notified if there is a collisions/deconfliction for my new term being registered to a languageSet | C45: EDLM - Requirements Management | G45: ADL Human Centered Design [EXT] | I45: Hunter Smith | R45: [LDSS] Edit a Language Set | S45: Medium | U45: ldss/openlxp-xss, ldss-xss/CCV-LCV | V45: ERM-539 | W45: Backlog | AA45: 0 | AB45: 0 | AC45: 0 | AD45: 0 | AE45: 0 | AF45: 0 | AG45: 0 | AH45: 0 | AK45: EDLM Glossary Manager
A46: Story | B46: As a [xBOM Manager], I would like to be notified when a new term is added to my LanguageSet (xBOM Type 2) | C46: EDLM - Requirements Management | G46: ADL Human Centered Design [EXT] | I46: Hunter Smith | R46: [LDSS] Edit a Language Set | S46: Medium | U46: ldss/openlxp-xss, ldss-xss/CCV-LCV | V46: ERM-540 | W46: Backlog | AA46: 0 | AB46: 0 | AC46: 0 | AD46: 0 | AE46: 0 | AF46: 0 | AG46: 0 | AH46: 0 | AK46: EDLM xBOM Manager
A47: Story | B47: As a [xBOM Manager], I would like to be notified when there are collisions / deconflictions with terms being added to my LanguageSet | C47: EDLM - Requirements Management | G47: ADL Human Centered Design [EXT] | I47: Hunter Smith | R47: [LDSS] Edit a Language Set | S47: Medium | U47: ldss/openlxp-xss, ldss-xss/CCV-LCV | V47: ERM-541 | W47: Backlog | AA47: 0 | AB47: 0 | AC47: 0 | AD47: 0 | AE47: 0 | AF47: 0 | AG47: 0 | AH47: 0 | AK47: EDLM xBOM Manager
A48: Epic | B48: [LDSS] Collaborate on a Language Set | C48: EDLM - Requirements Management | G48: ADL Human Centered Design [EXT] | I48: Hunter Smith | R48: Manage a Language Set | S48: Medium | U48: EDLM LDSS | V48: ERM-2101 | W48: Backlog | AA48: 0 | AB48: 0 | AC48: 0 | AD48: 0 | AE48: 0 | AF48: 0 | AG48: 0 | AH48: 0
A49: Initiative | B49: Manage xBOMs (Schemas) | C49: DLE - Top Level Planning | F49: ADL Human Centered Design [EXT] | G49: ADL Human Centered Design [EXT] | I49: Hunter Smith | R49: Configure: TLA Data Management | S49: Medium | V49: DTLP-56 | W49: Backlog | AA49: 0 | AB49: 0 | AC49: 0 | AD49: 0 | AE49: 1 | AF49: 0 | AG49: 0 | AH49: 1
A50: Epic | B50: [LDSS] Create xBOMs and Queryable Schemas | C50: EDLM - Requirements Management | F50: ADL Human Centered Design [EXT] | I50: Hunter Smith | R50: Manage xBOMs (Schemas) | S50: Medium | U50: ldss/openlxp-xss, ldss-xss/CCV-LCV | V50: ERM-436 | W50: Backlog | AA50: 0 | AB50: 0 | AC50: 0 | AD50: 0 | AE50: 10 | AF50: 0 | AG50: 0 | AH50: 10 | AK50: EDLM xBOM Manager, EDLM Glossary Manager
A51: Story | B51: As a [Glossary Manager] I would like to fully define termsets as an xBOM Type 2 Composite xBOM | C51: EDLM - Requirements Management | G51: ADL Human Centered Design [EXT] | I51: Florian Tolk | R51: [LDSS] Create xBOMs and Queryable Schemas | S51: Medium | U51: ldss/openlxp-xss, ldss-xss/CCV-LCV | V51: ERM-464 | W51: Backlog | AA51: 0 | AB51: 0 | AC51: 0 | AD51: 0 | AE51: 0 | AF51: 0 | AG51: 0 | AH51: 0 | AK51: EDLM Glossary Manager
A52: Story | B52: As a [xBOM Manager] I would like to be able to map my schema to P2881 Profiles? -SEE NOTES | C52: EDLM - Requirements Management | G52: ADL Human Centered Design [EXT] | I52: Hunter Smith | R52: [LDSS] Create xBOMs and Queryable Schemas | S52: Medium | U52: ldss/openlxp-xss, ldss-xss/CCV-LCV | V52: ERM-323 | W52: Backlog | AA52: 0 | AB52: 0 | AC52: 0 | AD52: 0 | AE52: 0 | AF52: 0 | AG52: 0 | AH52: 0 | AK52: EDLM xBOM Manager
A53: Story | B53: As a [xBOM Manager] I would lke to my uploaded schema's to be translated into the CDAO xBOM Format | C53: EDLM - Requirements Management | G53: ADL Human Centered Design [EXT] | I53: Hunter Smith | R53: [LDSS] Create xBOMs and Queryable Schemas | S53: Medium | U53: ldss/openlxp-xss, ldss-xss/CCV-LCV | V53: ERM-474 | W53: Backlog | AA53: 0 | AB53: 0 | AC53: 0 | AD53: 0 | AE53: 0 | AF53: 0 | AG53: 0 | AH53: 0 | AK53: EDLM xBOM Manager
A54: Story | B54: As a [Glossary Manager], I want to select a language set and add an [X]BOM to it | C54: EDLM - Requirements Management | G54: ADL Human Centered Design [EXT] | I54: Ashley Howell | R54: [LDSS] Create xBOMs and Queryable Schemas | S54: Medium | U54: ldss/openlxp-xss, ldss-xss/CCV-LCV | V54: ERM-999 | W54: Backlog | AA54: 0 | AB54: 0 | AC54: 0 | AD54: 0 | AE54: 0 | AF54: 1 | AG54: 0 | AH54: 1 | AK54: EDLM Glossary Manager
A55: Story | B55: As a [Glossary Manager], I want to search [X]BOMs to align to my selected language set | C55: EDLM - Requirements Management | G55: ADL Human Centered Design [EXT] | I55: Ashley Howell | R55: [LDSS] Create xBOMs and Queryable Schemas | S55: Medium | U55: ldss/openlxp-xss, ldss-xss/CCV-LCV | V55: ERM-1005 | W55: Backlog | AA55: 0 | AB55: 0 | AC55: 0 | AD55: 0 | AE55: 0 | AF55: 0 | AG55: 0 | AH55: 0 | AK55: EDLM Glossary Manager
A56: Story | B56: As an [xBOM Manager], I want to see my used/saved [X]BOMs | C56: EDLM - Requirements Management | G56: ADL Human Centered Design [EXT] | I56: Ashley Howell | R56: [LDSS] Create xBOMs and Queryable Schemas | S56: Medium | U56: ldss/openlxp-xss, ldss-xss/CCV-LCV | V56: ERM-1006 | W56: Backlog | AA56: 0 | AB56: 0 | AC56: 0 | AD56: 0 | AE56: 0 | AF56: 0 | AG56: 0 | AH56: 0 | AK56: EDLM xBOM Manager
A57: Story | B57: As a [Glossary Manager], I would like to see my saved [X]BOMs displayed within a table with sortable columns | C57: EDLM - Requirements Management | G57: ADL Human Centered Design [EXT] | I57: Ashley Howell | R57: [LDSS] Create xBOMs and Queryable Schemas | S57: Medium | U57: ldss/openlxp-xss, ldss-xss/CCV-LCV | V57: ERM-1007 | W57: Backlog | AA57: 0 | AB57: 0 | AC57: 0 | AD57: 0 | AE57: 0 | AF57: 0 | AG57: 0 | AH57: 0 | AK57: EDLM Glossary Manager
A58: Story | B58: As a [Glossary Manager], I want to filter [X]BOMs on [X]BOM type and [X]BOM component | C58: EDLM - Requirements Management | G58: ADL Human Centered Design [EXT] | I58: Ashley Howell | R58: [LDSS] Create xBOMs and Queryable Schemas | S58: Medium | U58: ldss/openlxp-xss, ldss-xss/CCV-LCV | V58: ERM-1008 | W58: Backlog | AA58: 0 | AB58: 0 | AC58: 0 | AD58: 0 | AE58: 0 | AF58: 0 | AG58: 0 | AH58: 0 | AK58: EDLM Glossary Manager
A59: Story | B59: As a [Glossary Manager] I want to be able to take defined terms, and link them to create an xBOM | C59: EDLM - Requirements Management | G59: ADL Human Centered Design [EXT] | I59: Florian Tolk | R59: [LDSS] Create xBOMs and Queryable Schemas | S59: Medium | V59: ERM-2624 | W59: Backlog | AA59: 0 | AB59: 0 | AC59: 0 | AD59: 0 | AE59: 0 | AF59: 0 | AG59: 0 | AH59: 0
A60: Story | B60: As a [System of Records] I want to query the XSS for Schemas/Profiles | C60: EDLM - Requirements Management | G60: ADL Human Centered Design [EXT] | I60: Florian Tolk | R60: [LDSS] Create xBOMs and Queryable Schemas | S60: Medium | V60: ERM-2625 | W60: Backlog | AA60: 0 | AB60: 0 | AC60: 0 | AD60: 0 | AE60: 0 | AF60: 0 | AG60: 0 | AH60: 0
A61: Initiative | B61: Experience Indexing | C61: DLE - Top Level Planning | F61: ADL Human Centered Design [EXT] | G61: ADL Human Centered Design [EXT] | I61: Hunter Smith | R61: Configure: TLA Data Management | S61: Medium | V61: DTLP-57 | W61: Backlog | AA61: 0 | AB61: 0 | AC61: 0 | AD61: 0 | AE61: 3 | AF61: 0 | AG61: 0 | AH61: 3
A62: Epic | B62: Create Indexing Agent | C62: EDLM - Requirements Management | G62: ADL Human Centered Design [EXT] | I62: Hunter Smith | R62: Experience Indexing | S62: Medium | V62: ERM-2260 | W62: Backlog | AA62: 0 | AB62: 0 | AC62: 0 | AD62: 0 | AE62: 0 | AF62: 0 | AG62: 0 | AH62: 0
A63: Epic | B63: Define Schema Endpoint(s) for agent to use | C63: EDLM - Requirements Management | G63: ADL Human Centered Design [EXT] | I63: Hunter Smith | R63: Experience Indexing | S63: Medium | V63: ERM-2261 | W63: Backlog | AA63: 0 | AB63: 0 | AC63: 0 | AD63: 0 | AE63: 0 | AF63: 0 | AG63: 0 | AH63: 0
A64: Epic | B64: Run Indexing Agent | C64: EDLM - Requirements Management | G64: ADL Human Centered Design [EXT] | I64: Hunter Smith | R64: Experience Indexing | S64: Medium | V64: ERM-2262 | W64: Backlog | AA64: 0 | AB64: 0 | AC64: 0 | AD64: 0 | AE64: 0 | AF64: 0 | AG64: 0 | AH64: 0
A65: Initiative | B65: Experience Management | C65: DLE - Top Level Planning | F65: ADL Human Centered Design [EXT] | G65: ADL Human Centered Design [EXT] | I65: Hunter Smith | R65: Configure: TLA Data Management | S65: Medium | V65: DTLP-58 | W65: Backlog | AA65: 0 | AB65: 0 | AC65: 0 | AD65: 0 | AE65: 5 | AF65: 0 | AG65: 0 | AH65: 5
A66: Epic | B66: Review Indexed Data in XIS | C66: EDLM - Requirements Management | G66: ADL Human Centered Design [EXT] | I66: Hunter Smith | R66: Experience Management | S66: Medium | V66: ERM-2264 | W66: Backlog | AA66: 0 | AB66: 0 | AC66: 0 | AD66: 0 | AE66: 0 | AF66: 0 | AG66: 0 | AH66: 0
A67: Epic | B67: Make Data Available | C67: EDLM - Requirements Management | G67: ADL Human Centered Design [EXT] | I67: Hunter Smith | R67: Experience Management | S67: Medium | V67: ERM-2265 | W67: Backlog | AA67: 0 | AB67: 0 | AC67: 0 | AD67: 0 | AE67: 0 | AF67: 0 | AG67: 0 | AH67: 0
A68: Epic | B68: Validate Indexed Data in the XMS | C68: EDLM - Requirements Management | G68: ADL Human Centered Design [EXT] | I68: Hunter Smith | R68: Experience Management | S68: Medium | V68: ERM-2266 | W68: Backlog | AA68: 0 | AB68: 0 | AC68: 0 | AD68: 0 | AE68: 0 | AF68: 0 | AG68: 0 | AH68: 0
A69: Epic | B69: Update Data (XMS) as Needed | C69: EDLM - Requirements Management | G69: ADL Human Centered Design [EXT] | I69: Hunter Smith | R69: Experience Management | S69: Medium | V69: ERM-2267 | W69: Backlog | AA69: 0 | AB69: 0 | AC69: 0 | AD69: 0 | AE69: 0 | AF69: 0 | AG69: 0 | AH69: 0
A70: Epic | B70: Review Validate Source data (.xls) | C70: EDLM - Requirements Management | G70: ADL Human Centered Design [EXT] | I70: Hunter Smith | R70: Experience Management | S70: Medium | V70: ERM-2268 | W70: Backlog | AA70: 0 | AB70: 0 | AC70: 0 | AD70: 0 | AE70: 0 | AF70: 0 | AG70: 0 | AH70: 0
A71: Use Case | B71: Configure: System Administration | C71: DLE - Top Level Planning | D71: ECCR MVP, ECCR FOC | F71: ADL Human Centered Design [EXT] | G71: ADL Human Centered Design [EXT] | I71: Hunter Smith | J71: Internal Grooming Sprint | N71: 46113 | S71: Medium | U71: EDLM Portal, edlm-portal/talent-manager-dashboard, edlm-portal/learning-plan | V71: DTLP-11 | W71: Backlog | AA71: 0 | AB71: 0 | AC71: 0 | AD71: 0 | AE71: 4 | AF71: 0 | AG71: 0 | AH71: 4
A72: Initiative | B72: Manage User Accounts | C72: DLE - Top Level Planning | D72: ECCR MVP, ECCR FOC | F72: ADL Human Centered Design [EXT] | G72: ADL Human Centered Design [EXT] | I72: Hunter Smith | J72: Internal Grooming Sprint | N72: 46113 | R72: Configure: System Administration | S72: Medium | U72: EDLM Portal, edlm-portal/talent-manager-dashboard, edlm-portal/learning-plan | V72: DTLP-10 | W72: Backlog | AA72: 0 | AB72: 0 | AC72: 0 | AD72: 0 | AE72: 5 | AF72: 0 | AG72: 0 | AH72: 5
A73: Epic | B73: EDLM: Add/Remove Users | C73: EDLM - Requirements Management | I73: Hunter Smith | O73: 46005 | R73: Manage User Accounts | S73: Medium | U73: EDLM Portal, edlm-portal/talent-manager-dashboard, edlm-portal/learning-plan | V73: ERM-1796 | W73: Backlog | AA73: 0 | AB73: 0 | AC73: 0 | AD73: 50 | AE73: 1 | AF73: 0 | AG73: 1 | AH73: 2 | AJ73: 45992 | AK73: EDLM IT System Administrator, EDLM IT System Admin
A74: Story | B74: As a [DoD Service Admin], I want to reach out to the Operations Center to create an account | C74: EDLM - Requirements Management | H74: Desiree Esiere | R74: EDLM: Add/Remove Users | S74: High | T74: Zendesk_DANTES | U74: EDLM Portal | V74: ERM-2852 | W74: Backlog | AA74: 0 | AB74: 0 | AC74: 0 | AD74: 0 | AE74: 0 | AF74: 0 | AG74: 0 | AH74: 0 | AK74: EDLM IT System Admin
A75: Epic | B75: View / Edit Users | C75: EDLM - Requirements Management | D75: ECCR MVP, ECCR FOC | F75: ADL Human Centered Design [EXT] | I75: Hunter Smith | J75: Internal Grooming Sprint | N75: 46113 | R75: Manage User Accounts | S75: Medium | U75: EDLM ECCR, mmt/mmt-portal, EDLM Portal, EDLM LDSS, edlm-portal/talent-manager-dashboard, edlm-portal/learning-plan, MMT Backend, eccr/cis, eccr/cds, eccr/cms, Zendesk | V75: ERM-1786 | W75: Backlog | AA75: 0 | AB75: 0 | AC75: 0 | AD75: 50 | AE75: 4 | AF75: 0 | AG75: 4 | AH75: 8 | AI75: 46035 | AK75: EDLM IT System Administrator, EDLM Org Execs/Manager, EDLM IT System Admin
A76: Story | B76: As an [Admin], I want to assign users to groups (e.g., working group, reviewers). | C76: EDLM - Requirements Management | E76: ECCR MVP | G76: ADL Human Centered Design [EXT] | K76: Internal Grooming Sprint [EXT] | R76: View / Edit Users | S76: High | U76: EDLM ECCR, eccr/cis, eccr/cds, eccr/cms | V76: ERM-2146 | W76: Prioritized | AA76: 0 | AB76: 0 | AC76: 0 | AD76: 0 | AE76: 0 | AF76: 0 | AG76: 0 | AH76: 0 | AK76: EDLM IT System Administrator
A77: Story | B77: As a [System Admin], I want users to login and access the site by using JWT and RBAC | C77: EDLM - Requirements Management | G77: ADL Human Centered Design [EXT] | I77: Hunter Smith | R77: View / Edit Users | S77: Medium | V77: ERM-2214 | W77: Backlog | AA77: 0 | AB77: 0 | AC77: 0 | AD77: 0 | AE77: 0 | AF77: 0 | AG77: 0 | AH77: 0
A78: Story | B78: As an [Admin], I want to assign framework-specific user permissions (create, view, edit, manage). | C78: EDLM - Requirements Management | E78: ECCR FOC | H78: Erin Perry | R78: View / Edit Users | S78: High | T78: ECCR | U78: EDLM ECCR, eccr/cis | V78: ERM-2441 | W78: Backlog | AA78: 0 | AB78: 0 | AC78: 0 | AD78: 0 | AE78: 0 | AF78: 0 | AG78: 0 | AH78: 0 | AK78: EDLM Competency Manager
A79: Story | B79: As an [Admin], I want to update/edit framework-specific user permissions (create, view, edit, manage). | C79: EDLM - Requirements Management | E79: ECCR FOC | H79: Erin Perry | R79: View / Edit Users | S79: High | T79: ECCR | U79: EDLM ECCR, eccr/cis | V79: ERM-2442 | W79: Backlog | AA79: 0 | AB79: 0 | AC79: 0 | AD79: 0 | AE79: 0 | AF79: 0 | AG79: 0 | AH79: 0 | AK79: EDLM Competency Manager
A80: Epic | B80: Modify existing user accounts (e.g., name changes, department transfers, notifications, preferences) | C80: EDLM - Requirements Management | F80: ADL Human Centered Design [EXT] | G80: ADL Human Centered Design [EXT] | I80: Hunter Smith | N80: 45541 | R80: Manage User Accounts | S80: Medium | V80: ERM-2379 | W80: Backlog | AA80: 0 | AB80: 0 | AC80: 0 | AD80: 0 | AE80: 2 | AF80: 0 | AG80: 0 | AH80: 2
A81: Story | B81: As a [Site Admin] I would like to be able to manage all users and data within the ECCR | C81: EDLM - Requirements Management | G81: ADL Human Centered Design [EXT] | I81: Florian Tolk | R81: Modify existing user accounts (e.g., name changes, department transfers, notifications, preferences) | S81: High | U81: eccr/frontend | V81: ERM-210 | W81: Backlog | AA81: 0 | AB81: 0 | AC81: 0 | AD81: 0 | AE81: 0 | AF81: 0 | AG81: 0 | AH81: 0 | AK81: EDLM IT System Administrator, EDLM Competency Manager
A82: Story | B82: As a [Learner], I want to set preferences for receiving notifications of different types via email or UI | C82: EDLM - Requirements Management | G82: ADL Human Centered Design [EXT] | I82: Ashley Howell | O82: 45541 | R82: Modify existing user accounts (e.g., name changes, department transfers, notifications, preferences) | S82: Medium | T82: Customer | V82: ERM-43 | W82: Backlog | AA82: 0 | AB82: 0 | AC82: 0 | AD82: 0 | AE82: 0 | AF82: 0 | AG82: 0 | AH82: 0 | AK82: EDLM Learner
A83: Epic | B83: Reset User Passwords and Enforce Password Policies | C83: EDLM - Requirements Management | R83: Manage User Accounts | S83: Medium | U83: EDLM Portal | V83: ERM-2803 | W83: Backlog | AA83: 0 | AB83: 0 | AC83: 0 | AD83: 0 | AE83: 0 | AF83: 0 | AG83: 0 | AH83: 0
A84: Epic | B84: Unlock User Accounts after Failed Login Attempts | C84: EDLM - Requirements Management | R84: Manage User Accounts | S84: Medium | U84: EDLM Portal | V84: ERM-2804 | W84: Backlog | AA84: 0 | AB84: 0 | AC84: 0 | AD84: 0 | AE84: 0 | AF84: 0 | AG84: 0 | AH84: 0
A85: Initiative | B85: Manage Access Control & Permissions | C85: DLE - Top Level Planning | F85: ADL Human Centered Design [EXT] | G85: ADL Human Centered Design [EXT] | I85: Hunter Smith | J85: Internal Grooming Sprint | N85: 46113 | R85: Configure: System Administration | S85: Medium | U85: EDLM Portal | V85: DTLP-80 | W85: Backlog | AA85: 0 | AB85: 0 | AC85: 0 | AD85: 0 | AE85: 2 | AF85: 0 | AG85: 0 | AH85: 2 | AI85: 46035
A86: Epic | B86: Assign Users to Groups or Roles (e.g. Active Directory Groups) | C86: EDLM - Requirements Management | F86: ADL Human Centered Design [EXT] | J86: Internal Grooming Sprint | N86: 46113 | R86: Manage Access Control & Permissions | S86: Medium | U86: EDLM Portal | V86: ERM-2826 | W86: Backlog | AA86: 0 | AB86: 0 | AC86: 0 | AD86: 0 | AE86: 1 | AF86: 0 | AG86: 0 | AH86: 1 | AI86: 46035 | AK86: EDLM IT System Admin
A87: Story | B87: As a [DANTES Admin], I want to assign/remove role permissions, so that each DANTES and Service Admin has the correct access level | C87: EDLM - Requirements Management | G87: ADL Human Centered Design [EXT] | H87: Desiree Esiere | K87: Internal Grooming Sprint [EXT] | R87: Assign Users to Groups or Roles (e.g. Active Directory Groups) | S87: Highest | T87: Zendesk_DANTES | U87: EDLM Portal | V87: ERM-2851 | W87: Prioritized | AA87: 0 | AB87: 0 | AC87: 0 | AD87: 100 | AE87: 0 | AF87: 0 | AG87: 1 | AH87: 1 | AK87: EDLM IT System Admin
A88: Epic | B88: View/Edit User Permissions | C88: EDLM - Requirements Management | F88: ADL Human Centered Design [EXT] | R88: Manage Access Control & Permissions | S88: Medium | U88: EDLM Portal, Zendesk | V88: ERM-2827 | W88: Backlog | AA88: 0 | AB88: 0 | AC88: 0 | AD88: 0 | AE88: 1 | AF88: 0 | AG88: 0 | AH88: 1 | AK88: EDLM IT System Admin
A89: Story | B89: As a [DoD Service Admin], I want to reach out to the Operations Center (DANTES Admin)to access my role assignments--so that I can confirm I have the correct permissions. | C89: EDLM - Requirements Management | G89: ADL Human Centered Design [EXT] | R89: View/Edit User Permissions | S89: High | T89: Zendesk_DANTES | U89: EDLM Portal, Zendesk | V89: ERM-2855 | W89: Backlog | AA89: 0 | AB89: 0 | AC89: 0 | AD89: 0 | AE89: 0 | AF89: 0 | AG89: 0 | AH89: 0 | AK89: EDLM IT System Admin
A90: Initiative | B90: Monitoring & Auditing | C90: DLE - Top Level Planning | F90: ADL Human Centered Design [EXT] | G90: ADL Human Centered Design [EXT] | I90: Hunter Smith | R90: Configure: System Administration | S90: Medium | U90: EDLM Portal | V90: DTLP-81 | W90: Backlog | AA90: 0 | AB90: 0 | AC90: 0 | AD90: 0 | AE90: 2 | AF90: 0 | AG90: 0 | AH90: 2
A91: Epic | B91: Track User Login/Logout Activity | C91: EDLM - Requirements Management | R91: Monitoring & Auditing | S91: Medium | U91: EDLM Portal | V91: ERM-2828 | W91: Backlog | AA91: 0 | AB91: 0 | AC91: 0 | AD91: 0 | AE91: 2 | AF91: 0 | AG91: 0 | AH91: 2 | AK91: EDLM IT System Admin
A92: Story | B92: As a [ADL Admin], I want to view user activity and see if they are about to be locked out, so I can determine if they still need access. | C92: EDLM - Requirements Management | H92: Desiree Esiere | R92: Track User Login/Logout Activity | S92: High | T92: Zendesk_DANTES | U92: EDLM Portal | V92: ERM-2853 | W92: Backlog | AA92: 0 | AB92: 0 | AC92: 0 | AD92: 0 | AE92: 0 | AF92: 0 | AG92: 0 | AH92: 0 | AK92: EDLM IT System Admin
A93: Story | B93: As a [DANTES Admin], I want to view <aca. Insti.> user activity and see if they are about to be locked out, so I can determine if they still need access. | C93: EDLM - Requirements Management | H93: Desiree Esiere | R93: Track User Login/Logout Activity | S93: High | T93: Zendesk_DANTES | U93: EDLM Portal | V93: ERM-2854 | W93: Backlog | AA93: 0 | AB93: 0 | AC93: 0 | AD93: 0 | AE93: 0 | AF93: 0 | AG93: 0 | AH93: 0 | AK93: EDLM IT System Admin
A94: Epic | B94: Audit data within the system | C94: EDLM - Requirements Management | F94: ADL Human Centered Design [EXT] | I94: Hunter Smith | R94: Monitoring & Auditing | S94: Medium | V94: ERM-3384 | W94: Backlog | AA94: 0 | AB94: 0 | AC94: 0 | AD94: 0 | AE94: 1 | AF94: 0 | AG94: 0 | AH94: 1
A95: Story | B95: As an Admin, I want to manage bad data (Update/Delete) for all data even if it is marked un-editable by its owner | C95: EDLM - Requirements Management | G95: ADL Human Centered Design [EXT] | R95: Audit data within the system | S95: Medium | V95: ERM-1543 | W95: Backlog | AA95: 0 | AB95: 0 | AC95: 0 | AD95: 0 | AE95: 0 | AF95: 0 | AG95: 0 | AH95: 0
A96: Initiative | B96: Identity & Identity Management | C96: DLE - Top Level Planning | G96: ADL Human Centered Design [EXT] | I96: Hunter Smith | R96: Configure: System Administration | S96: Medium | V96: DTLP-82 | W96: Backlog | AA96: 0 | AB96: 0 | AC96: 0 | AD96: 0 | AE96: 0 | AF96: 0 | AG96: 0 | AH96: 0
A97: Use Case | B97: System Orientation | C97: DLE - Top Level Planning | D97: ECCR IOC | F97: ADL Human Centered Design [EXT] | G97: ADL Human Centered Design [EXT] | I97: Hunter Smith | J97: Internal Grooming Sprint, MMT Sprint 16, MMT Sprint 18, SAPRO Sprint 10, SAPRO Sprint 11, SAPRO Sprint 3 | N97: 46146 | S97: Medium | V97: DTLP-71 | W97: Backlog | AA97: 0 | AB97: 0 | AC97: 0 | AD97: 0 | AE97: 2 | AF97: 0 | AG97: 0 | AH97: 2
A98: Initiative | B98: Access | C98: DLE - Top Level Planning | G98: ADL Human Centered Design [EXT] | I98: Hunter Smith | R98: System Orientation | S98: Medium | V98: DTLP-72 | W98: Backlog | AA98: 0 | AB98: 0 | AC98: 0 | AD98: 0 | AE98: 0 | AF98: 0 | AG98: 0 | AH98: 0
A99: Initiative | B99: Onboarding | C99: DLE - Top Level Planning | D99: ECCR IOC | F99: ADL Human Centered Design [EXT] | G99: ADL Human Centered Design [EXT] | I99: Hunter Smith | J99: Internal Grooming Sprint, MMT Sprint 16, MMT Sprint 18, SAPRO Sprint 10, SAPRO Sprint 11, SAPRO Sprint 3 | N99: 46146 | R99: System Orientation | S99: Medium | V99: DTLP-73 | W99: Backlog | AA99: 0 | AB99: 0 | AC99: 0 | AD99: 0 | AE99: 3 | AF99: 0 | AG99: 0 | AH99: 3
A100: Epic | B100: [SAPRO] _ Initial SARW-MS Deployment and Configuration | C100: EDLM - Requirements Management | J100: SAPRO Sprint 3 | K100: SAPRO Sprint 11 [EXT] + SAPRO Sprint 10 [EXT] [COMPLETED] | O100: 46146 | R100: Onboarding | S100: High | U100: EDLM Moodle LMS, EDLM Portal | V100: ERM-2690 | W100: Backlog | AA100: 0 | AB100: 0 | AC100: 0 | AD100: 50 | AE100: 0 | AF100: 1 | AG100: 1 | AH100: 2
...

Sheet ERM project with Parent
A1: Issue Type | B1: Issue key | C1: Issue id | D1: Summary | E1: Description | F1: Custom field (Acceptance Criteria) | G1: Custom field (Acceptance Criteria) | H1: Parent | I1: Parent key | J1: Parent summary | K1: Status | L1: Components | M1: Components | N1: Components | O1: Components | P1: Components | Q1: Components | R1: Components | S1: Components | T1: Components | U1: Components | V1: Components | W1: Components | X1: Components | Y1: Components | Z1: Components | AA1: Components | AB1: Components | AC1: Components | AD1: Components | AE1: Components | AF1: Labels | AG1: Labels | AH1: Labels | AI1: Labels | AJ1: Labels
A2: Epic | B2: ERM-3384 | C2: 11527177 | D2: Audit data within the system | H2: 11522561 | I2: DTLP-81 | J2: Monitoring & Auditing | K2: Backlog
A3: Epic | B3: ERM-3383 | C3: 11527175 | D3: View Dashboards to monitor and relfect on progress and performance | H3: 11527173 | I3: DTLP-92 | J3: Monitor Staffing Plan | K3: Backlog
A4: Story | B4: ERM-3382 | C4: 11527171 | D4: As a Learner, I want to see which courses align with the my targeted role or specific competency gap | H4: 11517533 | I4: ERM-1096 | J4: [Portal] Identify Learning Activities or Courses for Learning Plan | K4: Backlog
A5: Story | B5: ERM-3381 | C5: 11527169 | D5: As a Learner, I want to see the percentage of competency alignment for courses that teach competencies aligned to my goal(s) | H5: 11517533 | I5: ERM-1096 | J5: [Portal] Identify Learning Activities or Courses for Learning Plan | K5: Backlog
A6: Story | B6: ERM-3379 | C6: 11526932 | D6: As a [Org (NOVA) Admin], I want to view and sort or organize individual applicant data | E6: As a NOVA Admin, I want to view and organize individual applicant data so I can easily manage all applications assigned to me during the current application cycle. In the SAPRO Portal, I can see a clear count of the total number of active applications I have, and I can use a global search bar to quickly locate an applicant by name. To help me narrow and reorganize the list, I can apply filters for *Application Type* (New or Renewal) and *Position*, and I can sort the table by key fields—including *Last Name*, *First Name*, *Type*, *Position*, and *Received Date*. This allows me to structure the data in the way that best supports my review workflow. From the table, I can view each individual application or download the applicant’s full packet directly from the portal. I also have access to full pagination controls, enabling me to navigate through large volumes of applications efficiently. | F6: Viewing Applications Given I am logged into the SAPRO Portal When I land on the Applications page Then I should see a table listing all applications assigned to me And I should see the total number of active applications displayed Searching for an Applicant Given I am on the Applications page When I enter a name into the search bar And I click the search icon or press enter Then the table should update to show only applications matching my search term Filtering Applications Scenario: Filter by Application Type Given application type filters are visible When I select “New” or “Renewal” Then the table should display only applications that match the selected type Scenario: Filter by Position Given position filters are visible When I select one or more positions Then the table should display only applications for those positions Scenario: Clear All Filters Given I have applied one or more filters When I click “Clear All Filters” Then all filters should be removed And the full list of applications should be displayed Sorting Applicant Data Scenario: Sort by Last Name Given the table contains applicant data When I click the “Last Name” column header Then the data should sort in ascending order And when I click it again Then it should sort in descending order Repeat logic for each sortable column: - First Name - Type - Position - Received Date Viewing and Downloading Applications Scenario: View Application Given I am on the Applications page When I click “View Application” for an applicant Then the system should open or display the application details Scenario: Download Application Given I am on the Applications page When I click “Download Application” Then the application file should begin downloading to my device Pagination Given there are more applications than can fit on one page When I use the pagination controls (page numbers or previous/next) Then I should be able to navigate between pages of applications Scenario: Jump to Page Given I see the “Jump to” pagination control When I enter a page number and click “Go” Then I should be taken directly to that page of results | H6: 11526586 | I6: ERM-3368 | J6: Package Application | K6: Backlog | L6: EDLM Portal | AF6: SAPRO
A7: Story | B7: ERM-3378 | C7: 11526728 | D7: As a [Academic Institution Registrar], I want to opt in/out of transcript status update notifications | E7: As an Academic Institute using the MMT Portal, I want a *Settings* page—reachable from the left navigation and from the profile menu in the top‑right—where I can see *all notification types available for my role* and *opt in or out of email notifications* at a big and at a small level, so I can control what updates I receive and where they are delivered. When I *opt into email notifications*, I can toggle individual event types: * *Delivered* and the page clearly displays the *email address* where my updates will be sent. If I *turn off* email notifications, the per‑event toggles become disabled to make it obvious I won’t receive any emails. Whenever my *transcript status is updated*, I receive an *email notification* that uses the approved template for the corresponding status. Templates: DELIVERED Dear User, Your Academic Institute has received a transcript from a DoD Service Member. Please log in to the MMT Portal ([+https://mmt.dso.mil/academicInstitute+|https://mmt.staging.dso.mil/academicInstitute]) to review the details and take any necessary actions. Thank you for using the MMT system. [MMT Portal Access Link] | F7: Background: An Academic Institute is logged into the MMT Portal. The user has access to a Settings page, accessible from both the left navigation and the profile menu in the top-right. The Settings page displays all notification types available for the user’s role and allows the user to opt in or out of email notifications at both a global and per-event level. The page also displays the email address where notifications will be sent. Scenario 1: Accessing the Settings Page Given the user is logged into the MMT Portal When the user clicks on "Settings" from the left navigation or the profile menu Then the user is taken to the Settings page And the page displays all notification types available for the user’s role And the page displays the email address where notifications will be sent Scenario 2: Opting In to Email Notifications Given the user is on the Settings page And email notifications are currently turned off When the user toggles the global email notifications switch to "On" Then the per-event notification toggles ("Delivered") become enabled And the user can select which event types to receive email notifications for Scenario 3: Opting Out of Email Notifications Given the user is on the Settings page And email notifications are currently turned on When the user toggles the global email notifications switch to "Off" Then all per-event notification toggles become disabled And it is visually clear that no email notifications will be sent Scenario 4: Per-Event Notification Toggle Given the user has email notifications turned on When the user toggles the "Delivered" event notification on or off Then the system updates the user’s preferences for that event type And only selected event types will trigger email notifications Scenario 5: Displaying Notification Email Address Given the user is on the Settings page When the page loads Then the email address where notifications will be sent is clearly displayed Scenario 6: Transcript Status Update - Delivered Given the user has opted in to receive "Delivered" email notifications When the user’s transcript status is updated to "Delivered" Then the user receives an email notification using the approved "DELIVERED" template And the email includes a link to the MMT Portal ( Appgate SDP) Scenario 7: No Email Sent When Opted Out Given the user has opted out of all email notifications When the user’s transcript status is updated to any status Then the user does not receive any email notification | H7: 11523053 | I7: ERM-2636 | J7: [MMT] Monitor Application | K7: To Do
A8: Story | B8: ERM-3377 | C8: 11526727 | D8: As a [Service Member/Veteran], I want to opt in/out of transcript status update notifications | E8: As a Service Member using the MMT Portal, I want a *Settings* page—reachable from the left navigation and from the profile menu in the top‑right—where I can see *all notification types available for my role* and *opt in or out of email notifications* at a big and at a small level, so I can control what updates I receive and where they are delivered. When I *opt into email notifications*, I can toggle individual event types: * *Delivered* * *Accessed* and the page clearly displays the *email address* where my updates will be sent. If I *turn off* email notifications, the per‑event toggles become disabled to make it obvious I won’t receive any emails. Whenever my *transcript status is updated*, I receive an *email notification* that uses the approved template for the corresponding status. Templates: DELIVERED Dear User, Your transcript has been successfully *delivered* to an academic institution. Please log in to the MMT Portal ([https://mmt.apps.dso.mil/|https://mmt.apps.dso.mil/|smart-link] ) to review the details and take any necessary actions. Thank you for using the MMT system. [MMT Portal Access Link] ACCESSED Dear User, Your transcript has been successfully *accessed* by an academic institution. Please log in to the MMT Portal ([https://mmt.apps.dso.mil/|https://mmt.apps.dso.mil/|smart-link] ) to review the details and take any necessary actions. Thank you for using the MMT system. [MMT Portal Access Link] | F8: Background: A Service Member or Veteran is logged into the MMT Portal. The user has access to a Settings page, accessible from both the left navigation and the profile menu in the top-right. The Settings page displays all notification types available for the user’s role and allows the user to opt in or out of email notifications at both a global and per-event level. The page also displays the email address where notifications will be sent. Scenario 1: Accessing the Settings Page Given the user is logged into the MMT Portal When the user clicks on "Settings" from the left navigation or the profile menu Then the user is taken to the Settings page And the page displays all notification types available for the user’s role And the page displays the email address where notifications will be sent Scenario 2: Opting In to Email Notifications Given the user is on the Settings page And email notifications are currently turned off When the user toggles the global email notifications switch to "On" Then the per-event notification toggles ("Delivered", "Accessed") become enabled And the user can select which event types to receive email notifications for Scenario 3: Opting Out of Email Notifications Given the user is on the Settings page And email notifications are currently turned on When the user toggles the global email notifications switch to "Off" Then all per-event notification toggles become disabled And it is visually clear that no email notifications will be sent Scenario 4: Per-Event Notification Toggle Given the user has email notifications turned on When the user toggles the "Delivered" or "Accessed" event notification on or off Then the system updates the user’s preferences for that event type And only selected event types will trigger email notifications Scenario 5: Displaying Notification Email Address Given the user is on the Settings page When the page loads Then the email address where notifications will be sent is clearly displayed Scenario 6: Transcript Status Update - Delivered Given the user has opted in to receive "Delivered" email notifications When the user’s transcript status is updated to "Delivered" Then the user receives an email notification using the approved "DELIVERED" template And the email includes a link to the MMT Portal ( Appgate SDP) Scenario 7: Transcript Status Update - Accessed Given the user has opted in to receive "Accessed" email notifications When the user’s transcript status is updated to "Accessed" Then the user receives an email notification using the approved "ACCESSED" template And the email includes a link to the MMT Portal ( Appgate SDP) Scenario 8: No Email Sent When Opted Out Given the user has opted out of all email notifications When the user’s transcript status is updated to any status Then the user does not receive any email notification | H8: 11523053 | I8: ERM-2636 | J8: [MMT] Monitor Application | K8: To Do
A9: Story | B9: ERM-3373 | C9: 11526658 | D9: As a [Learner], I want to upload certifications for CEU courses I have taken | E9: This requirement would only appear for Renewal applications. For each course I add to my ‘Completed Continuing Education Hours’ section, I want to upload a file of my certification that shows I completed that course. | H9: 11523894 | I9: ERM-2865 | J9: Initiate Application | K9: Backlog
A10: Story | B10: ERM-3371 | C10: 11526623 | D10: As a [Learner], I want to read and acknowledge the code of ethics so it is clear that I understand them | E10: * As a [Learner], I want to read and acknowledge the code of ethics during the application process so that it is clear I understand and agree to the ethical standards required. * The application must present the full text of the code of ethics to the learner. * The learner must be required to check a box or provide an electronic signature to acknowledge they have read and understood the code of ethics before proceeding. * This step is mandatory and must be completed before the application can be submitted. * The system should track this acknowledgment (e.g., via an xAPI statement) for auditing and compliance purposes. * This requirement is part of the MVP and should be included under the "initiate application" workflow. Here is the updated Code of Ethics Language: Every DoD Sexual Assault Response Workforce (SARW) Professional must act with integrity, treat all victims of sexual assault crimes with dignity and compassion, and uphold principles of justice for accused and accuser alike. To these ends, this Code will govern the conduct of DoD SARW Professionals: I. In relationships with every victim, the DoD SARW professionals shall: # Recognize the interests of the victim as a primary responsibility. # Respect the victim's civil and legal rights, subject only to laws requiring disclosure of information to appropriate other sources. # Respect the victim's rights to privacy and confidentiality, subject only to laws requiring disclosure. # Respond compassionately to each victim with personalized services. # Accept the victim's statement of events as it is told, withholding opinion or judgment, whether or not a suspected offender has been identified, arrested, convicted, or acquitted. # Provide services to every victim, within policy guidelines set by the DoD and the Services, without attributing blame, no matter what the victim's conduct was at the time of the victimization or at another stage of the victim’s life. # Foster maximum self-determination on the part of the victim. # Serve as a victim advocate when assigned, and in that capacity, act on behalf of the victim's stated needs and within policy guidelines set by DoD and the Services. # Should one victim's needs conflict with another's, act with regard to one victim only after promptly referring the other to another qualified DoD SARW professional. # Have no personal or sexual relations with victims currently supported by DoD SARW professionals or with alleged offenders, in recognition that to do so risks exploitation of the knowledge and trust derived from the professional relationship. # Make victim referrals to other resources or services only in the victim's best interest, avoiding any conflict of interest in the process, and do so in accordance with DoD regulations. II. In relationships with colleagues, other professionals, and the public, the DoD SARW professionals shall: # Conduct relationships with colleagues in such a way as to promote mutual respect and improvement of service. # Conduct relationships with allied professionals such that they are given equal respect and dignity as professionals in the victim assistance field. # Take steps to quell negative, insubstantial rumors about colleagues and allied professionals. # Share knowledge and encourage proficiency and excellence in victim assistance among colleagues and allied professionals, paid and volunteer. # Provide professional support, guidance, and assistance to new DoD SARW professionals to the field in order to promote consistent quality and professionalism in victim assistance. # Obey all applicable Federal, DoD, and Service laws and regulations. III. In her or his professional conduct, the SARC/SAPR VA shall: # Maintain high personal and professional standards in the capacity of a service provider and advocate for victims. # Seek and maintain a proficiency in the delivery of services to victims. # Not discriminate against any victim, employee, colleague, allied professional, or member of the public on the basis of age, sex, disability, ethnicity, race, national origin, religious belief, or sexual orientation. # In accordance with restricted reporting, applicable privileged communications, and all applicable Federal, DoD, and Service privacy laws and regulations, respect the privacy of information provided by the victims served before, during, and after the course of the professional relationship. # Clearly distinguish in public statements representing one's personal views from positions adopted by organizations for which she or he works or is a member, in accordance with Service policy. # Not use her or his official position to secure gifts, monetary rewards, or special privileges or advantages. # Notify competent authorities of the conduct of any colleague or allied professional that constitutes mistreatment of a victim or that brings the profession into disrepute. # Notify competent authorities of any conflict of interest that prevents oneself or a colleague from being able to provide competent services to a victim, or from working cooperatively with colleagues or allied professionals in a victim being impartial in the assistance of any victim. # Notify competent authority immediately if charged, arrested, and/or convicted of any criminal activity. IV. In her or his responsibility to any other profession, the DoD SARW professional will be bound by the ethical standards of the allied profession of which she or he is a member. ---- The certification language is as follows: Certification: I, the undersigned applicant, hereby certify that I have read and agree to follow the Code of Professional Ethics for DoD SARW professionals. I understand that the D-SAACP Certification is subject to surrender on demand to my SARW Program Administrator for cause, and this action may be listed in my permanent record. [ ] I acknowledge that I have read and understand the Code of Ethics for DoD SARW Professionals. | F10: Feature: Learner acknowledges the Code of Ethics As a Learner I want to read and acknowledge the Code of Ethics So that it is clear that I understand them Scenario: Learner views the Code of Ethics Given the learner is logged into the portal When the learner hits 'continue' on the 'Privacy Act Statement Page' they are navigated to the Code of Ethics page Then the learner should see the full text of the Code of Ethics And the learner should have the option to scroll through the content And the learner should see a 'Certification' box where they can acknowledge that they have read and understand the Code of Ethics. Scenario: Learner acknowledges the Code of Ethics Given the learner has viewed the Code of Ethics When the learner clicks the "Acknowledge" checkbox Then the system should record the learner’s acknowledgement And display a confirmation that the acknowledgement was successful Scenario: Learner cannot proceed without acknowledgement Given the learner has not yet acknowledged the Code of Ethics When the learner attempts to submit / initiate application Then the system should prompt the learner to read and acknowledge the Code of Ethics first (mark as incomplete) Scenario: System stores acknowledgement Given the learner has acknowledged the Code of Ethics When an administrator reviews learner records Then the acknowledgement status should be visible within the learner’s application And the timestamp of acknowledgement should be recorded Scenario: Learner re-reads the Code of Ethics Given the learner has already acknowledged the Code of Ethics When the learner navigates back to the Code of Ethics page Then the learner should be able to view the content again And the acknowledgement status should remain recorded | H10: 11523894 | I10: ERM-2865 | J10: Initiate Application | K10: In Progress
A11: Story | B11: ERM-3370 | C11: 11526622 | D11: As a [Learner], I want breadcrumbs that allow me to navigate to different sections of my application | E11: I want persistent breadcrumbs when I start/re-enter my application for every section of the application so I can have visibility on where I am at, AND so I can navigate to different sections as needed. There are 4 types of breadcrumbs: *New Applications - ‘DoD Civilian Sexual Assault Response Workforce Professional’ Position* * Privacy Act > Code of Ethics > Applicant Info > Job Shadow Experience > Recommendations > Review & Send *New Applications - All other Positions* * Privacy Act > Code of Ethics > Applicant Info > Job Shadow Experience > Review & Send *Renewal Applications - ‘DoD Civilian Sexual Assault Response Workforce Professional’ Position* * Privacy Act > Code of Ethics > Applicant Info > Recommendations > CEU Documentation > Review & Send *Renewal Applications - All other Positions* * Privacy Act > Code of Ethics > Applicant Info > CEU Documentation > Review & Send | F11: Background: The application process includes multiple sections. Users need persistent breadcrumbs to see their current location and navigate between sections. There are four breadcrumb flows, depending on application type and position. Scenario 1: New Application – ‘DoD Civilian Sexual Assault Response Workforce Professional’ Position Given the user is starting or re-entering a new application for the ‘DoD Civilian Sexual Assault Response Workforce Professional’ position When the application loads Then the breadcrumb should display: Privacy Act > Code of Ethics > Applicant Info > Job Shadow Experience > Recommendations > Review & Send And the current section should be visually highlighted And the user should be able to click any previous section in the breadcrumb to navigate to it Scenario 2: New Application – All Other Positions Given the user is starting or re-entering a new application for any position other than ‘DoD Civilian Sexual Assault Response Workforce Professional’ When the application loads Then the breadcrumb should display: Privacy Act > Code of Ethics > Applicant Info > Job Shadow Experience > Review & Send And the current section should be visually highlighted And the user should be able to click any previous section in the breadcrumb to navigate to it Scenario 3: Renewal Application – ‘DoD Civilian Sexual Assault Response Workforce Professional’ Position Given the user is starting or re-entering a renewal application for the ‘DoD Civilian Sexual Assault Response Workforce Professional’ position When the application loads Then the breadcrumb should display: Privacy Act > Code of Ethics > Applicant Info > Recommendations > CEU Documentation > Review & Send And the current section should be visually highlighted And the user should be able to click any previous section in the breadcrumb to navigate to it Scenario 4: Renewal Application – All Other Positions Given the user is starting or re-entering a renewal application for any position other than ‘DoD Civilian Sexual Assault Response Workforce Professional’ When the application loads Then the breadcrumb should display: Privacy Act > Code of Ethics > Applicant Info > CEU Documentation > Review & Send And the current section should be visually highlighted And the user should be able to click any previous section in the breadcrumb to navigate to it Scenario 5: Breadcrumb Persistence Given the user navigates between sections of the application When the user moves to a new section Then the breadcrumb should update to reflect the current section And the breadcrumb should remain visible and accurate throughout the application process Scenario 6: Navigation via Breadcrumb Given the user is on any section of the application When the user clicks a previous section in the breadcrumb Then the application should navigate to the selected section And the breadcrumb should update to highlight the new current section | H11: 11523894 | I11: ERM-2865 | J11: Initiate Application | K11: To Do
A12: Story | B12: ERM-3369 | C12: 11526620 | D12: As a [Learner], I want to read a privacy act statement prior to entering in my application information. | E12: Applicant will be able to read the privacy act statement and navigate back to it in the breadcrumbs if needed. Here is the updated Privacy Act Statement Language: Privacy Act Statement *AUTHORITY:* 10 U.S.C. 136, Under Secretary of Defense for Personnel and Readiness; and DoD Instruction 6495.03, Defense Sexual Assault Advocate Certification Program (D-SAACP). *PRINCIPAL PURPOSE(S):* The information on this form will be used to review and process Defense Sexual Assault Advocate Certification Program (D-SAACP) applications for all eligible Department of Defense (DoD) Sexual Assault Response Workforce (SARW) personnel. *ROUTINE USE(S):* To the Department of Justice Office for Victims of Crime and Training Technical Assistance Center for the purpose of verifying certified DoD SARW personnel for participation in Advance Military Sexual Assault Advocate Training. Additional routine uses may be found in the applicable system of records notice DHRA 10, Defense Sexual Assault Advocate Certification Program at: [https://dpcld.defense.gov/Privacy/SORNsIndex/DOD-wide-SORN-Article-View/Article/570562/dhra-10-dod/|https://dpcld.defense.gov/Privacy/SORNsIndex/DOD-wide-SORN-Article-View/Article/570562/dhra-10-dod/|smart-link] *DISCLOSURE:* Mandatory. If you are in an authorized DoD SARW position and you do not complete this form to receive your D-SAACP certification, you will be disqualified from the position. 10 U.S.C. 1561 | F12: Background: Given the user is completing the application form Scenario: Display Privacy Act Statement before application entry Given the user is about to begin the application When the application form loads Then display the full Privacy Act Statement as provided in the ticket description And require the user to view the statement before entering any application information Scenario: Breadcrumb navigation to Privacy Act Statement Given the user is navigating the application form When the user views any step of the application Then display breadcrumb navigation including a link labeled "Privacy Act Statement" And allow the user to return to the Privacy Act Statement at any time Scenario: Privacy Act Statement content accuracy Given the user is viewing the Privacy Act Statement When the statement is displayed Then ensure the text matches exactly the language provided in the ticket, including bold headings and the SORN hyperlink Scenario: Accessibility of Privacy Act Statement Given the user is viewing the Privacy Act Statement When the statement is displayed Then ensure the statement is accessible (screen reader compatible, sufficient contrast, resizable text) | H12: 11523894 | I12: ERM-2865 | J12: Initiate Application | K12: In Progress
A13: Epic | B13: ERM-3368 | C13: 11526586 | D13: Package Application | H13: 11522515 | I13: DTLP-70 | J13: Application Processing | K13: Backlog | L13: EDLM Portal | AF13: SAPRO
A14: Business Requirement | B14: ERM-3366 | C14: 11526519 | D14: The EDLM portal backend shall have an application model to store inputs from the DSAACP application | K14: In Progress | L14: EDLM Portal
A15: Business Requirement | B15: ERM-3365 | C15: 11526486 | D15: The EDLM portal backend shall have an experience model to track and store inputs from the DSCAAP Application | E15: Data Mapping for reference: [20251104_SAPRO Data Fields.xlsx|https://adloffice365.sharepoint.com/:x:/s/EDLM_Extranet/IQCm3aqGu2oPR5FKT4B69P-PAa2mQDBqaiOiYkKTYRDol7s?e=MJkqSH] | K15: In Progress | L15: EDLM Portal
A16: Business Requirement | B16: ERM-3339 | C16: 11526410 | D16: Moodle configurations to outline cohort capabilities and permissions | E16: Ticket for Moodle configuration, adding Moodle documentation for reference. DHRA brand guideline can be found here [DOW Brand Guide | U.S. Department of War|https://www.war.gov/Brand-Guide/] *Moodle Ticket Description:* * Configure the DHRA Moodle instance to support theming for different cohorts or organizational groups (e.g., SAPRO, DHRA), allowing each group to have distinct visual branding as specified in their respective style guides. * Ensure the Moodle landing page presents a DHRA-branded entry point, with navigation to individual cohort/group pages. * Reference and implement branding elements (logo, fonts, colors) from the uploaded DHRA and SAPRO style guides. * Document any technical limitations or dependencies related to theming and cohort separation, especially regarding Edwiser plugin functionality. * This configuration is intended as a bare-bones MVP to demonstrate scalability for additional DHRA organizations in the future. | K16: To Do
A17: Business Requirement | B17: ERM-3335 | C17: 11526342 | D17: EDLM Portal shall store personnel information in support of the DSAACP application intake | E17: Build out data fields for DSAACP application - the data will NOT be prepopulated as a part of this ticket. Create APIs for editing fields. Data mapping spreadsheet for reference: [https://adloffice365.sharepoint.com/:x:/s/EDLM_Extranet/IQCm3aqGu2oPR5FKT4B69P-PAa2mQDBqaiOiYkKTYRDol7s?e=MSnd5S|https://adloffice365.sharepoint.com/:x:/s/EDLM_Extranet/IQCm3aqGu2oPR5FKT4B69P-PAa2mQDBqaiOiYkKTYRDol7s?e=MSnd5S|smart-link] | H17: 11515253 | I17: ERM-138 | J17: Portal: Baseline Functional Requirements | K17: In Progress | L17: EDLM Portal
A18: Story | B18: ERM-3330 | C18: 11526269 | D18: As a [Learner], I want to be notified of expiring certification so I can ensure I complete renewal requirements | E18: certification expires every XX years/months. Users should be sent an email reminder XX months prior to expiration. in UI displaying past applications, there should be an indicator of upcoming expiry as well. _User should also see a notification in their learning summary_ | F18: Feature: Learner Certification Expiry Notifications As a Learner I want to be notified of expiring certification So that I can ensure I complete renewal requirements on time Scenario: Learner receives advance notification of certification expiry Given I have an active certification with a defined expiry date When the certification is 90 days from expiry Then I should receive a notification reminding me of the upcoming expiry And the notification should include instructions for renewal Scenario: Learner receives reminder closer to expiry Given I have an active certification with a defined expiry date When the certification is 30 days from expiry Then I should receive a notification reminding me of the upcoming expiry And the notification should include a link to renewal requirements Scenario: Learner receives final reminder before expiry Given I have an active certification with a defined expiry date When the certification is 7 days from expiry Then I should receive a final notification warning me of imminent expiry And the notification should highlight urgent action required Scenario: Learner views certification status Given I am logged into the system When I navigate to my certification dashboard Then I should see the expiry date for each certification And it should indicate if the expiry date is approaching Scenario: Learner completes renewal requirements Given I have received a notification of expiring certification When I complete the renewal requirements (apply as renewal applicant, be approved) Then my certification status should update to "Renewed" And I should receive a confirmation notification of successful renewal/ re-certification Scenario: Certification expires without renewal Given I have not completed renewal requirements When the certification expiry date passes Then my certification status should update to "Expired" And I should receive a notification informing me that the certification has expired | K18: Backlog
A19: Story | B19: ERM-3326 | C19: 11526262 | D19: As a [Learner], I want to select the type, frequency, and method for how I am receiving notifications. | E19: we should have US for this already in existing Baseline capabilities. Configure to SAPRO specific notifications. UI & email notifications? | F19: Feature: Learner Notification Preferences As a Learner I want to select the type, frequency, and method for how I am receiving notifications So that I can control how I stay informed without being overwhelmed Scenario: Learner selects notification type Given I am logged into the system When I navigate to the notification settings Then I should be able to choose notification types such as "Application Status", "Course Updates", and "Certificate Issuance" And my selection should be saved and applied to future notifications Scenario: Learner selects notification frequency Given I am on the notification settings page When I choose a frequency option such as "Immediate", "Daily Summary", or "Weekly Digest" Then the system should deliver notifications according to my chosen frequency And I should receive a confirmation of my preference change Scenario: Learner selects notification method Given I am on the notification settings page When I choose a method such as "Email" or "In-App" Then the system should deliver notifications using my selected method And I should be able to update or change this method at any time Scenario: Learner updates preferences Given I have previously set notification preferences When I change the type, frequency, or method Then the system should immediately update my preferences And I should receive a confirmation message of the updated settings Scenario: Learner disables notifications Given I am on the notification settings page When I choose to disable a notification type Then I should no longer receive notifications of that type And the system should reflect the disabled status in my settings Scenario: Learner views current preferences Given I am logged into the system When I navigate to the notification settings Then I should see my current selections for type, frequency, and method And each preference should be clearly displayed and editable | H19: 11523898 | I19: ERM-2867 | J19: Monitor Application Intake and Validation | K19: Backlog
A20: Story | B20: ERM-3322 | C20: 11526255 | D20: As a [Learner], I want to monitor my application status all the way through submission, final approval, and certificate issuance | E20: For MVP, these may be email notification rather than in-app? Applicants should receive notifications of their application’s progress, creating improved transparency throughout the process. Applicants will also be able to view their application status in the ‘applications’ page. | F20: Feature: Learner Application Status Tracking and Notifications As a Learner I want to be notified and keep track of my application status So that I am aware of progress from submission to certificate issuance Scenario: Learner submits an application Given I have completed and submitted my application When the system receives my application Then I should see my application status as "Submitted" And I should receive a notification confirming submission Scenario: Application moves to review stage Given my application has been submitted When the application is under review Then I should see my application status as "In Review" And I should receive a notification that my application is being reviewed Scenario: Application receives final approval Given my application is under review When the application is approved Then I should see my application status as "Approved" And I should receive a notification confirming approval Scenario: Certificate is issued Given my application has been approved When the certificate is generated Then I should see my application status as "Certificate Issued" And I should receive a notification with details on accessing my certificate Scenario: Learner views application history Given I am logged into the system When I navigate to my application dashboard Then I should see a timeline of statuses including "Submitted", "In Review", "Approved", and "Certificate Issued" And each status should display the corresponding date and notification details | H20: 11523898 | I20: ERM-2867 | J20: Monitor Application Intake and Validation | K20: Backlog
A21: Story | B21: ERM-3314 | C21: 11526181 | D21: As a [Learner], I want to download my completed application | E21: After I have completed my application, and it has been filled out completely by the required individuals (e.g., SARC, Supervisor, CO, previous Supervisors…) I want to be able to access it, view my application and download it so I can share it or discuss it as/if needed. Updated Form TBD. | F21: Scenario: Learner downloads a completed application successfully Given the learner has initiated the application and all reviewers have complete their section and the application has been sent to NOVA. And the learner is logged into the system When the learner navigates to the "My Applications" page And selects the completed application And clicks the "Download" button Then the system should generate a downloadable file of the application And the file format should be PDF And the download should start automatically And the file should contain all submitted application details Scenario: Download option is not available for incomplete applications Given the learner has an application that is not yet completed When the learner views the application details Then the "Download" button should not be visible Scenario: Error handling when download fails Given the learner has completed and submitted the application And the learner is logged into the system When the learner clicks the "Download" button And the system encounters an error generating the file Then the system should display an error message | H21: 11523894 | I21: ERM-2865 | J21: Initiate Application | K21: Backlog | AF21: SAPRO
A22: Business Requirement | B22: ERM-3311 | C22: 11526113 | D22: . Any updates made shall be saved and reflected accurately in future IDP views or exports. | K22: To Do
A23: Business Requirement | B23: ERM-3310 | C23: 11526112 | D23: Any updates made shall be saved and reflected accurately in future IDP views or exports. | E23: *Title:* ERM-2468 Sub – Persist Updates Across IDP Views/Exports *Description:* Any updates made shall be saved and reflected accurately in future IDP views or exports. *Acceptance Criteria:* * Changes persist after session ends. * Exported IDP matches latest saved version. * Version control maintained for audit. | H23: 11515245 | I23: ERM-136 | J23: TM: Learning and Development | K23: Backlog
A24: Business Requirement | B24: ERM-3309 | C24: 11526111 | D24: Only user-editable sections may be changed; system-generated data shall remain locked. | E24: *Title:* ERM-2468 Sub ticket – Lock System-Generated Data *Description:* Only user-editable sections may be changed; system-generated data shall remain locked. *Acceptance Criteria:* * Editable fields: goals, objectives, activities. * Locked fields: personnel data, system-calculated metrics. * Attempted edits on locked fields trigger error message. | H24: 11515245 | I24: ERM-136 | J24: TM: Learning and Development | K24: Done
A25: Business Requirement | B25: ERM-3308 | C25: 11526110 | D25: The Learner shall be able to download or share the completed IDP with their supervisor. | E25: *Title:* ERM-2468 Sub ticket – Enable Download/Share of Completed IDP *Description:* The learner shall be able to download or share the completed IDP with their supervisor. *Acceptance Criteria:* * Download option available in PDF format. * Share option sends IDP via secure link or email to supervisor. * Audit log captures share/download actions. | H25: 11515245 | I25: ERM-136 | J25: TM: Learning and Development | K25: Backlog
A26: Business Requirement | B26: ERM-3307 | C26: 11526109 | D26: The generated IDP shall include auto-filled updated goals, selected objectives, and activities. | E26: *Title:* ERM-2468 Sub ticket – Include Auto-Filled Data in IDP *Description:* The generated IDP shall include auto-filled personnel data, updated goals, selected objectives, and activities. *Acceptance Criteria:* * Goals, objectives, and activities reflect latest updates. * Template formatting remains consistent. | H26: 11515245 | I26: ERM-136 | J26: TM: Learning and Development | K26: Testing In Progress
A27: Business Requirement | B27: ERM-3306 | C27: 11526108 | D27: The system shall auto-compile updated IDP information into the official IDP template | E27: ERM-2468 Subticket – Auto-Compile IDP into Official Template *Description:* The system shall auto-compile updated IDP information into the official IDP template (e.g., PDF format) upon save/export. *Acceptance Criteria:* * When a learner saves or exports, the system generates a PDF using the official template. * All updated objectives and activities are included. * No manual intervention required for compilation. *Priority:* Match ERM-2468 (likely P1). | H27: 11515245 | I27: ERM-136 | J27: TM: Learning and Development | K27: Backlog
A28: Business Requirement | B28: ERM-3305 | C28: 11526075 | D28: The ECCR shall allow a search for all competencies in its database | E28: The ECCR shall have a search capability for a user to search for all existing public competencies on multiple fields | K28: Backlog | L28: eccr/cis | M28: eccr/cms | N28: EDLM ECCR
A29: Business Requirement | B29: ERM-3304 | C29: 11526074 | D29: The ECCR shall allow users to copy existing competencies to a new draft framework | E29: When making/editing a Framework, users should have a search option for existing competencies that can be copied to a framework. This will create a new competency, with the copier being the owner | K29: Backlog | L29: eccr/cis | M29: eccr/cms | N29: EDLM ECCR
A30: Business Requirement | B30: ERM-3303 | C30: 11526073 | D30: The ECCR shall allow users to link existing competencies to a new draft framework | E30: When making/editing a Framework, users should have a search option for existing competencies that can be linked to a framework. This will not create a new competency, only link an existing competency to this framework | K30: Backlog | L30: eccr/cis | M30: eccr/cms | N30: EDLM ECCR
A31: Business Requirement | B31: ERM-3272 | C31: 11525917 | D31: Update CMS-UI unit test coverage above 80% | K31: Done
A32: Business Requirement | B32: ERM-3271 | C32: 11525916 | D32: Limit MMT Metrics dashboard for SVC MEMBER ADVOCATE | E32: limit metrics to only show based on the service the current SMA is part of | K32: Done
A33: Story | B33: ERM-3269 | C33: 11525882 | D33: As a [Org (SAPRO) Admin], I want to be able to access and view certification applications | E33: Allow me to review applications without the need to download. I want to do this all digitally. Review the application, attached documents etc.. The system should also include any relevant data from continous vetting process or any other systems that is not required by the applicant to add but still required for verificationa | F33: Feature: Access and View Certification Applications As an Org (SAPRO) Admin I want to be able to access and view certification applications So that I can review and manage applicant submissions Scenario: Admin accesses certification applications list Given the Admin is logged into the system When the Admin navigates to the certification applications section Then the system should display a list of all certification applications And each application should show applicant name, submission date, and current status Scenario: Admin searches for a certification application Given the Admin is on the certification applications list When the Admin enters search criteria (e.g., applicant name, application ID) Then the system should filter and display matching applications And the Admin should be able to access the details of the filtered applications Scenario: Admin sorts certification applications Given the Admin is viewing the certification applications list When the Admin selects a sort option (e.g., by submission date, status) Then the system should reorder the applications accordingly And the Admin should see the updated list Scenario: Admin accesses application history Given the Admin is viewing a certification application When the Admin selects the option to view application history Then the system should display a log of actions taken on the application And the log should include dates, times, and user identifiers | H33: 11523892 | I33: ERM-2864 | J33: Review and Complete Application | K33: Ready for Joint Grooming | L33: EDLM Portal | AF33: Admin | AG33: SAPRO
A34: Story | B34: ERM-3268 | C34: 11525881 | D34: As a [Org (SAPRO) Admin], I want to mark an application as reviewed and complete so that I know it is ready for submission to the next person | E34: Allow me to verify the application for accuracy. Once i mark the application verified it should automatically move to the next person in the verification flow. | F34: Feature: Mark Application as Reviewed and Complete As an Org (SAPRO) Admin I want to mark an application as reviewed and complete So that I know it is ready for submission to the next person Scenario: Admin marks application as reviewed Given the Admin has finished reviewing an applicant’s application And all required fields are complete and accurate When the Admin selects the option to mark the application as reviewed Then the system should update the application status to “Reviewed” Scenario: Admin marks application as complete Given the Admin has marked the application as reviewed When the Admin confirms the application is complete Then the system should update the application status to “Complete” And the application should be flagged as ready for submission to the next person Scenario: Prevent marking incomplete applications as complete Given the Admin is reviewing an application When the application has missing or incorrect information Then the system should prevent the Admin from marking the application as complete And the Admin should be prompted to resolve the issues (/pass back to applicant to resolve) before proceeding Scenario: Application appears in next person’s queue Given the Admin has marked the application as complete When the next person logs into the system Then the application should appear in their queue And the status should indicate “Ready for Next Review” Scenario: Audit trail of review and completion Given the Admin has marked the application as reviewed and complete When the system updates the application record Then the audit log should record the Admin’s actions And include the date, time, and Admin’s identifier | H34: 11523892 | I34: ERM-2864 | J34: Review and Complete Application | K34: Ready for Joint Grooming | L34: EDLM Portal | AF34: Admin | AG34: SAPRO
A35: Story | B35: ERM-3266 | C35: 11525879 | D35: As a [Org (SAPRO) Admin], I want to complete the digital letter of recommendation for applicants assigned to me. | E35: Feature: Complete Digital Letter of Recommendation Provide me the appropriate recommendation template digitally with most of the information pre-populated. | F35: Feature: Complete digital letter of recommendation for assigned applicants As an Org (SAPRO) Admin I want to complete the digital letter of recommendation for applicants assigned to me So that the recommendation is submitted and available for review in the system Scenario: Access assigned applicants Given I am logged in as an Org (SAPRO) Admin When I navigate to the "Assigned Applicants" section Then I should see a list of applicants assigned to me Scenario: Open digital letter of recommendation form Given I am viewing an applicant assigned to me When I select "Complete Letter of Recommendation" Then I should be presented with the digital recommendation form Scenario: Fill out recommendation form Given I am on the digital recommendation form When I enter all required fields (e.g., applicant details, recommendation text, rating) Then the system should validate that all mandatory fields are completed Scenario: Save draft of recommendation Given I am filling out the recommendation form When I click "Save & Exit" Then the system should store my progress without submitting the recommendation And I should be able to reopen and edit the draft later Scenario: Submit completed recommendation Given I have completed all required fields in the recommendation form When I click "Submit" (after completing any other relevant sections of app form) Then the system should mark the recommendation as completed And the applicant’s record should show the recommendation as submitted Scenario: Prevent submission of incomplete recommendation Given I have not filled out all required fields in the recommendation form When I attempt to click "Submit" Then the system should display an error message And prevent submission until all required fields are completed Scenario: Confirmation of submission Given I have submitted a completed recommendation Then I should see a confirmation message And the recommendation should be locked from further editing | H35: 11523892 | I35: ERM-2864 | J35: Review and Complete Application | K35: Ready for Joint Grooming | L35: EDLM Portal | AF35: Admin | AG35: SAPRO
A36: Story | B36: ERM-3264 | C36: 11525877 | D36: As a [Org (SAPRO) Admin], I want to monitor application progress | E36: BRAINSTORMING: PROCESS = which phase the application is in… indicator or problem, stuck or failed a step in the process?? example phases / steps … * *Application Intake & Validation* * *Review & Approval Workflow* ** Multi-level review (Evaluator → Supervisor → SAPRO Admin) * *Credential Verification* ** {color:#bf2600}Check applicant eligibility against suspended/revoked lists. [do we have a requirement for this?] {color} ** Validate training completion (e.g., IVAC, ethics, Safe Helpline). * *Training & CEU Compliance* ** Confirm required 40-hour NACP training and CEU course eligibility. ** Standardize clock-hour calculations and documentation uploads. [[SAPRO Data Fields | Meeting]|https://teams.microsoft.com/l/meeting/details?eventId=AAMkADVkZTE1MWRjLWMzZWYtNDdhOC1hMWViLTk5NGEwMjJhZjgzNQBGAAAAAACaXF_IfWguQpNkSFj645JWBwAV4EYqmMrDQoyoP60KlrJMAAAAAAENAAAV4EYqmMrDQoyoP60KlrJMAARFx6uOAAA%3d] * *Digital approval & Attestation* ** Decide if a single attestation checkbox suffices or multiple signatures are needed. ** Track signature placement and approval timestamps | F36: Feature: Monitor Application Progress As an Org (SAPRO) Admin I want to monitor application progress So that I can track applicant status and ensure timely completion Scenario: Admin views application progress dashboard Given the Admin is logged into the system When the Admin navigates to the application progress dashboard Then the system should display a list of all applicants relevant to Admin (i.e. admin is their supervisor/ writing letter of rec etc.) And each applicant should have a visible progress status (e.g., Not Started, In Progress, Submitted, Reviewed) along with the task required of the Admin and relevant dates Scenario: Admin identifies stalled applications Given the Admin is monitoring application progress When an application has not advanced for a defined period Then the system should flag the application as stalled / coming up to deadline And the Admin should be able to view which step is pending and if it's a task assigned to them as admin | H36: 11523898 | I36: ERM-2867 | J36: Monitor Application Intake and Validation | K36: Ready for Joint Grooming | L36: EDLM Portal | AF36: Admin | AG36: NOVA
A37: Story | B37: ERM-3263 | C37: 11525876 | D37: As a [Org (NOVA) Admin], I want to monitor application progress | E37: determine & validate the steps / phases NOVA admin would want monitor … e.g., * Application intake and validation * Application packaging/preparation * Review board assignment * Approval and certification leverage existing approach to displaying progress !image-20251118-213248.png|width=466,alt="image-20251118-213248.png"! | F37: Feature: Monitor Application Progress As an Org (NOVA) Admin I want to monitor application progress So that I can track applicant status and ensure timely completion Scenario: Admin views application progress dashboard Given the Admin is logged into the system When the Admin navigates to the application progress dashboard Then the system should display a list of all applicants And each applicant should have a visible progress status (e.g., Not Started, In Progress, Submitted, Reviewed) Scenario: Admin views detailed progress of a single applicant Given the Admin is on the application progress dashboard When the Admin selects a specific applicant Then the system should display the applicant’s detailed progress And the details should include completed steps, pending steps, and submission date Scenario: Admin monitors overall progress statistics Given the Admin is on the application progress dashboard When the Admin requests overall progress statistics Then the system should display aggregated data (e.g., percentage of applications submitted, reviewed, pending) Scenario: Admin identifies stalled applications Given the Admin is monitoring application progress When an application has not advanced for a defined period Then the system should flag the application as stalled And the Admin should be able to view which step is pending Scenario: Admin exports progress data Given the Admin is monitoring application progress When the Admin requests an export of progress data Then the system should generate a report with applicant statuses And the report should be available in a standard format (e.g., CSV, PDF) | H37: 11523900 | I37: ERM-2868 | J37: Monitor Application Processing | K37: Backlog | L37: EDLM Portal | AF37: Admin | AG37: SAPRO
A38: Story | B38: ERM-3262 | C38: 11525875 | D38: As a [Org (SAPRO) Admin], I want to be notified when an applicant re-submits their application after they fixed errors in their application so I can ensure they were corrected. | E38: I think(?) applicants are currently sent canned messages. Perhaps this is email notification that they need to contact XX. | F38: Scenario: SAPRO admin had flagged errors in Applicant's application and are waiting for Applicant to fix and re-submit Given: The applicant has received the Admin's comment requiring edits, and has made the edits then re-submitted When: The applicant re-submits Then: The Admin receives an (email and in-app?) notification saying "[Applicant Name] has edited their application and re-submitted. Click to review again" or something similar that links to the section of the application they edited. | H38: 11523898 | I38: ERM-2867 | J38: Monitor Application Intake and Validation | K38: Backlog | L38: EDLM Portal | AF38: Admin | AG38: SAPRO
A39: Story | B39: ERM-3261 | C39: 11525874 | D39: As a [Org (SAPRO) Admin], I want to provide notification and information of errors or missing information that needs to be fixed on an Applicants application. | E39: applicants are currently sent canned messages. Perhaps this is email notification that they need to contact XX. | F39: Feature: Applicant Application Error Notification As an Org (SAPRO) Admin I want to provide notification and information of errors or missing information So that applicants can correct and resubmit their applications Scenario: Admin identifies missing information in an application Given an applicant has submitted an application with missing required fields When the Admin reviews the application And the Admin marks the missing fields Then the system should generate a notification to the applicant And the notification should clearly list the missing information Scenario: Admin identifies errors in an application Given an applicant has submitted an application with incorrect data When the Admin reviews the application And the Admin flags the incorrect data Then the system should generate a notification to the applicant And the notification should clearly describe the errors Scenario: Applicant receives notification Given the Admin has flagged errors or missing information When the system sends a notification Then the applicant should receive the notification via the designated channel (e.g., email, portal message) And the notification should include instructions on how to correct the application Scenario: Applicant corrects and resubmits application Given the applicant has received a notification of errors or missing information When the applicant updates the application with the required corrections And resubmits the application Then the Admin should receive a notification And be able to review the corrected application And the system should mark the application as updated | H39: 11523892 | I39: ERM-2864 | J39: Review and Complete Application | K39: Backlog | L39: EDLM Portal | AF39: Admin | AG39: SAPRO
A40: Story | B40: ERM-3260 | C40: 11525873 | D40: As a [Org (SAPRO) Admin], I want to be able to use a check box (as a proxy for a digital signature) on required sections so that the system can track completion information. | E40: SAPRO admin completes a task and needs to indicate it is complete via a checkbox Checkboxes need to be inserted on several different screens to indicate completion of different tasks by different users. Checks need to be captured / logged in the system (name, title, date, time) For *renewal* applications Specific tasks include: * Verification of sexual assault victim advocacy experience * Evaluation of sexual assault victim advocacy experience * Supervisor and Commander statement of understanding * for SARCs and SAPR-VAs Recommendation by Supervisor * Documentation of Continuing Education Training Courses For *new* applications Specific tasks include: * Verification of sexual assault victim advocacy experience * Evaluation of sexual assault victim advocacy experience * Supervisor and Commander statement of understanding * for SARCs and SAPR-VAs Recommendation by Supervisor | F40: For all checkboxes for all SAPRO Admin roles [Supv, CO, SARC) associated with the tasks listed above .. when the check box is clicked, a popup box appears requesting confirmation of signature. When confirmation is made, data are captured in the system. and the box is filled in Scenario 1: Approve Application Using Checkbox Given The Org (SAPRO) Admin is reviewing an application for certification. Variations [new / renewal] The application meets all approval requirements. When The admin selects the digital checkbox affirming the information is accurate. Then The system records the approval action with the admin’s identity and timestamp. The application status changes to Approved. [ready to be processed by NOVA] The system removes the requirement for CAC-based digital signature. Scenario 2: Confirmation of Approval Given The admin has checked the approval box. When The system processes the approval action. Then A confirmation message appears: “Application approved successfully.” The approval is logged in the audit trail for compliance. Scenario 3: Security and Permissions Given The admin is logged in with valid credentials. When The admin attempts to approve an application using the checkbox. Then The system verifies the admin’s role and permissions before allowing the action. Unauthorized users cannot see or use the approval checkbox. | H40: 11523892 | I40: ERM-2864 | J40: Review and Complete Application | K40: Ready for Joint Grooming | L40: EDLM Portal | AF40: Admin | AG40: SAPRO
A41: Story | B41: ERM-3222 | C41: 11525767 | D41: As a [Learner], I want to see incorrect items I need to fix on my application prior to submitting it. | E41: Like not completing all of the required fields, entering the wrong type/format of information. -user input an email that does not end in .mil or .gov !image-20251202-170307 (1b9476dc-1589-4c71-8856-fa35d1e84948).png|width=250,alt="image-20251202-170307.png"! -user input a phone number in an invalid format / did not select/input DSN code (to be in mockup) [contains a non-numeric character / wrong amount of numbers ] | F41: Background: Given the user is completing the application form Scenario: Validate Email Domain Given the user enters an email address When the email does not end with ".mil" or ".gov" Then display an error message "Please provide a valid .mil or .gov email address" And prevent form submission Scenario: Validate Phone Number Format and DSN selection Given the user enters a phone number When the phone number format is invalid [e.g., non-numeric character] or the DSN code is not selected Then display an error message "Phone number format invalid. Include DSN code." And prevent form submission (Might get removed) Scenario: Validate Advocacy Experience documentation when claiming > 3,900 hours Given the user answers "Yes" to "Do you have more than 3,900 hours of Sexual Assault Victim Advocacy Experience within the past two years?" When the user does not provide documentation for at least 3,900 hours Then display an error message "Upload documentation for 3,900 hours of advocacy experience" And prevent form submission (Might get removed) Scenario: Validate selection of 3 experiences for evaluation when claiming > 3,900 hours Given the user answers "Yes" to "Do you have more than 3,900 hours of Sexual Assault Victim Advocacy Experience within the past two years?" When the user does not mark at least 3 experiences for evaluation Then display an error message "Select at least 3 experiences for evaluation" And prevent form submission Scenario: Validate CEU documentation total Given the user needs to enter CEU hours When the user does not supply 32 hours of documented, new CEU Then display an error message "Provide documentation for 32 hours of CEU" And prevent form submission | H41: 11523894 | I41: ERM-2865 | J41: Initiate Application | K41: To Do | L41: EDLM Portal | AF41: SAPRO
A42: Story | B42: ERM-3221 | C42: 11525766 | D42: As a [Learner], I want to see incomplete items I need to fix on my application prior to submitting it. | E42: Being able to see sections greyed out in the end if they dont pass validation. | F42: Scenario1 : The applicant has reached then end of the application but hasn't completed all items Given: They have not filled out all required fields When: They reach the final page of the application before clicking submit Then: The system will highlight incomplete items in an overview and not allow them to submit the application until they are remedied Scenario 2: The applicant has reached the end of the application and has filled out all required fields Given: They have filled out all required fields When: they reach the final page of the application to review before submitting Then: the system will mark all sections and items as complete and allow them to submit | H42: 11523894 | I42: ERM-2865 | J42: Initiate Application | K42: To Do | L42: EDLM Portal | AF42: SAPRO
A43: Story | B43: ERM-3220 | C43: 11525765 | D43: As a [Learner], I want to receive validation that all required data fields have been entered prior to submitting. | E43: the UI should provide a red asterisks indicating required fields. If a user tries to submit and a required field is empty, the form should not be submitted and the missing field(s) should be highlighted red. Applicant will be allowed to save content during application however before the final submission, the required fields will highlight red to indicate required fields. | F43: Scenario: The applicant believes they have completed all fields and is ready to submit their application for review Given: They have filled out all the required fields When: They reach the end of the application Then: the system will show all fields as complete in an overview and allow them to submit Given: The applicant has NOT filled out all required fields When: they reach the end of the application Then: the system will highlight incomplete fields in an overview and NOT allow them to submit until they fix the incomplete fields | H43: 11523894 | I43: ERM-2865 | J43: Initiate Application | K43: To Do | L43: EDLM Portal | AF43: SAPRO
A44: Story | B44: ERM-3219 | C44: 11525764 | D44: As a [Learner], I want to upload required D-SAACP certification as required for a new application | E44: When the applicant is selecting “which type of application are you submitting?” and they select “New Application,” then the applicant will be prompted to upload their certificate from their completed D-SAACP pre-approved training course(s). Learner must upload the requisite Sexual Assault Prevention and Response Office (DoD SAPRO) approved training course(s). Applicants will have the ability to upload multiple course certificates to account for situations where there are one or more required training courses. ---- NOTE: We will be using Drupal for document storage. | F44: ackground: Given the applicant is completing the application form and is selecting the type of application to submit Scenario: Prompt for Certificate Upload on New Application Given the applicant is on the application form And the applicant selects “New Application” for “Which type of application are you submitting?” When the applicant proceeds to the next step Then prompt the applicant to upload their certificate(s) from completed D-SAACP pre-approved training course(s) And display instructions that the certificate(s) must be from Sexual Assault Prevention and Response Office (DoD SAPRO) approved training courses Scenario: Allow Multiple Certificate Uploads Given the applicant is prompted to upload D-SAACP pre-approved training course certificates When the applicant has completed more than one required training course Then allow the applicant to upload multiple course certificates Scenario: Prevent Submission Without Required Certificate(s) Given the applicant has selected “New Application” When the applicant attempts to submit the application without uploading at least one D-SAACP pre-approved training course certificate Then display an error message “Upload at least one certificate from a completed D-SAACP pre-approved training course” And prevent form submission Scenario: Store Uploaded Certificates in Drupal Given the applicant uploads certificate(s) as part of the application When the upload is successful Then store the uploaded certificate(s) in Drupal for document storage | H44: 11523894 | I44: ERM-2865 | J44: Initiate Application | K44: To Do | L44: EDLM Portal | AF44: SAPRO
A45: Story | B45: ERM-3218 | C45: 11525763 | D45: As a [Learner], once I submit my application it should move to the next person in the chain for review and approvals | E45: New Application: * IF ‘DoD Civilian Sexual Assault Response Workforce Professional’ THEN Letter of Rec needed from a *Supervisor* * IF ‘Collateral Duty or Special Assignment SARC or SAPR VA’ THEN Statement of Understanding from their *Commander* is needed. * Job Shadowing approvals needed from supervisor (TBD). Renewal Application: ---- there is a linear chain of approvals / reviews. applicant to applicant supervisor for approval, then to 'appropriate' SARC for validation, then to NOVA admin. NOTE: The specific individuals and emails are required fields entered by the applicant. [This is correct, yes?] [~accountid:712020:53512bfe-51b0-4356-9c18-a0290c197cd3] [~accountid:609007a8f0db130069a66376] is the below correct? routing 1 → applicant to supervisor (found in required field in the application) routing 2--> supervisor to SARC (found in required field in the application) routing 3--> SARC to CO (found in required field in the application) CO to NOVA Admin (?) not sure where this will be found. | F45: Scenario 1: Successful Submission and Routing Given: • The learner has completed all required fields in the application. • The application is in Draft/In Progress status. When: • The learner clicks Submit. Then: • The system validates the application and confirms submission with a success message. • The application status changes to Submitted. • The application is routed to the next reviewer in the approval chain. • The next reviewer receives a notification and can access the application. • An audit log entry is created with submission details. DO WE WANT TO INCLUDE A LOCKING FEATURE? where only 1 person can edit the APPLICATION at a time? Scenario 2: Post-Submission Restrictions Given: • The learner has successfully submitted the application. When: • The learner attempts to edit the application. Then: • The system prevents edits unless workflow rules explicitly allow changes. • A message informs the learner that the application is locked for review. | H45: 11523894 | I45: ERM-2865 | J45: Initiate Application | K45: Internal Grooming | L45: EDLM Portal | AF45: SAPRO
A46: Story | B46: ERM-3217 | C46: 11525762 | D46: As a [Learner], I want to fill out information about my job shadow experience | E46: NOTE: This requirement would only appear for New applicants. the system will allow the applicant to enter metadata about their 90-day job shadowing experience. These fields will include: * position name * start date * end date * hours completed * supervisor last name * supervisor first name * supervisor email ---- IN THE FUTURE, THIS COULD COME FROM ELRR: Specific [Learner] data elements on the DD form that should come from ELRR: What IS included in the ELRR: * Position Name * Employment Dates * *tries to populate supervisor name from the system it came from (if available) What is needs to be edited: * Hours * Supervisor Name * Supervisor Email Calculation of Hours: * *estimates hours based off the dates ← Deloitte to discuss if feasible/what the LOE is. ---- Data fields from HR System / ELRR: * 4.1.10.15 hasEmploymentRecord >> 4.1.8.10 Position * 4.1.10.15 hasEmploymentRecord >> 4.1.8.XX ApplicationId (Extension) * 4.1.3.4 LastName * 4.1.3.2 FirstName * Derive from 4.1.3.3 MiddleName OR 4.1.3.XX (Extension) - 4.1.3.57 HasMilitaryRecord - 4.1.10.1 militarybranch * 4.1.3.57 HasMilitaryRecord - 4.1.10.7 MilitaryCurrentStatus * 4.1.3.57 HasMilitaryRecord - 4.1.10.6 MilitaryCurrentRank * 4.1.3.57 HasMilitaryRecord - 4.1.10.31 CurrentPayGrade * 4.1.3.57 HasMilitaryRecord - 4.1.10.24 isEmployedBy - 4.1.7.1 OrganizationName * 4.1.3.57 HasMilitaryRecord - 4.1.10.24 isEmployedBy - 4.1.7.4 Facility or 4.1.7.5 Department * 4.1.3.57 HasMilitaryRecord - 4.1.10.24 isEmployedBy - 4.1.7.31 hasEmail * 4.1.3.57 HasMilitaryRecord - 4.1.10.24 isEmployedBy - 4.1.7.30 hasPhone * 4.1.3.57 HasMilitaryRecord - 4.1.10.24 isEmployedBy - 4.1.7.30 hasPhone | F46: Feature: Select courses and experiences for advocacy application As a Learner, I want to select courses and experiences from my learner profile So that I can include relevant advocacy experience in my application. Scenario: Learner selects courses and experiences from profile Given the Learner is logged into the system And the Learner has completed courses and experiences listed in their profile When the Learner accesses the application form And selects courses and experiences to include Then the selected items should be added to the advocacy experience section of the application And the system should confirm the inclusion of selected items And the Learner should be able to review and edit the selection before submission Scenario: Learner has no courses or experiences in profile Given the Learner is logged into the system And the Learner accesses the application form When the system checks the learner profile for courses and experiences And finds no entries Then the system should display a message indicating no experiences are available And provide guidance on how to add or record relevant experiences And prevent the learner from selecting empty experience fields | H46: 11523894 | I46: ERM-2865 | J46: Initiate Application | K46: Backlog | L46: EDLM Portal | AF46: SAPRO
A47: Story | B47: ERM-3216 | C47: 11525761 | D47: As a [Learner], I want to add courses and experiences (CEU) to be included in my application (continuing education) | E47: This is only applicable for Renewal Applicants. DECISION 12/16: We will move forward with importing a sample extract of courses from JKO, NOVA, Coursera…etc. or other sources in order to showcase the capability. The learner will then select that course or enter in a course manually. If a learner selects a course from the pre-defined list, then the metadata will autopopulate the fields (where possible). To discuss further: applicant will need to upload proof of certification for each CEU course listed. ---- Design Notes: notes from 11/25 meeting with Andy for CEU on HOW it will be implemented: * NOTE: we want to limit options to courses that haven’t been listed yet on the application. * we are pulling/or will be pulling from 3 datasets: ** (FUTURE) xapi statements from known courses. xAPI. from ELRR completed statements. course completions that we know of that are showing up for xAPI statements. *** ECC statements. course categories are the course competencies. course category would be an extension in ECC. ** (MVP) known sapro courses (where we dontl know if completion or not) *** ECC statements. course categories are the course competencies. course category would be an extension in ECC. ** (MVP) Manually added courses – aka something brand new. ** (FUTURE) integrate ElasticSearch in search/dropdown ---- NOTE: We need to get req'd/approaved courses into ECC NOTE: requires use of simulated data until we get [Learner] record integration ---- Current Design implementation: * Dropdown has a search and filtering functionality. Users can select from bottom option to add manually instead. * Courses that aren’t eligible will be greyed out. Tooltip will provide info as to why its greyed out. Business logic for MVP: * List of approved SAPRO courses from ECC that can be counted as CEU hours * (MVP Only) no filter for if course is eligible to be included (eligibility = whether or not learner included this course in a previous application; with the exception of the ‘Ethics’ and ‘SAFE Helpline 101’, Safe Helpline 102’ course) * (MVP) hardcode SAPRO courses * (MVP) manual entry of courses if they are not in the ‘SAPRO’ approved list. * (MVP) will not include xAPI statements | F47: Scenario: A renewal applicant is adding their CEU (continuing education) hours to their application Given: They have taken the pre-approved courses and the courses are reflected on their learner profile When: they query the ECC they can search through their learner profile AND the broader course catalog for relevant courses Then: they can select which courses are relevant that they've taken to add to their CEU section of the application Given: The applicant has taken courses not listed in the ECC / are not reflected on their learner profile When: they get to the CEU portion of the application Then: they can manually input course information and upload proof / certification | H47: 11523894 | I47: ERM-2865 | J47: Initiate Application | K47: To Do | L47: EDLM Portal | AF47: SAPRO
A48: Story | B48: ERM-3215 | C48: 11525760 | D48: As a [Learner], I want to see information for how to update pre-populated personal and organizational information so I can correct any errors | E48: How does this info get back into the system? We talked about submitting a ticket? | F48: Scenario: Learner (Applicant) is completing the DSACCP application and needs to provide personal info, job info, learning history, etc. Given: The applicant is viewing a page with pre-populated information When: The applicant hovers over a tool tip Then: the applicant will see information about where their info is being pulled from and if they can /how to edit it When: the applicant tries to edit a field (changing pre-populated field) Then: the applicant can change the information, saving it as data tied to the application (not to the system it pulled from to pre-populate) MVP: allow applicant to edit information instead of requesting edits to parent system. | H48: 11523894 | I48: ERM-2865 | J48: Initiate Application | K48: Backlog | L48: EDLM Portal | AF48: SAPRO
A49: Story | B49: ERM-3214 | C49: 11525759 | D49: As a [Learner], I want my personal and organizational information pre-populated so that I don't have to re-enter data the system should already have | E49: Pull from the ELRR to populate as many fields as possible. Identify from data model what specific fields will be pre-populated. All fields are required unless listed as optional. ---- ELRR Data fields: * Applicant First Name * Applicant Last Name * Applicant Middle Initial * Affiliation * Status * Rank * Grade Editable fields include: * Command * Installation * Work email address * DSN *_(optional data field)_* * Work telephone number * Phone Number ext. *_(optional data field)_* * SARC’s Email address *ELRR Supports all of these fields* ---- Data fields from HR System / ELRR: * 4.1.10.15 hasEmploymentRecord >> 4.1.8.10 Position * 4.1.10.15 hasEmploymentRecord >> 4.1.8.XX ApplicationId (Extension) * 4.1.3.4 LastName * 4.1.3.2 FirstName * Derive from 4.1.3.3 MiddleName OR 4.1.3.XX (Extension) - 4.1.3.57 HasMilitaryRecord - 4.1.10.1 militarybranch * 4.1.3.57 HasMilitaryRecord - 4.1.10.7 MilitaryCurrentStatus * 4.1.3.57 HasMilitaryRecord - 4.1.10.6 MilitaryCurrentRank * 4.1.3.57 HasMilitaryRecord - 4.1.10.31 CurrentPayGrade * 4.1.3.57 HasMilitaryRecord - 4.1.10.24 isEmployedBy - 4.1.7.1 OrganizationName * 4.1.3.57 HasMilitaryRecord - 4.1.10.24 isEmployedBy - 4.1.7.4 Facility or 4.1.7.5 Department * 4.1.3.57 HasMilitaryRecord - 4.1.10.24 isEmployedBy - 4.1.7.31 hasEmail * 4.1.3.57 HasMilitaryRecord - 4.1.10.24 isEmployedBy - 4.1.7.30 hasPhone * 4.1.3.57 HasMilitaryRecord - 4.1.10.24 isEmployedBy - 4.1.7.30 hasPhone ---- Design / Development Decision: We will move forward with fields we CAN gather from JWT, to get some data fields. The remainder of fields will be editable. As we connect to source HR systems, we can populate more fields and slowly move towards read only, where applicable. ---- Note on the below - need to determine validity of the data coming in via JWT with P1 on how we are receiving this information, most likely would recommend pulling from HR system and only CAC info from JWT. Data fields from JWT: "preferred_username": "jdoe", "given_name": "John", "activecac": "DOE.JOHN.1234567890" "name": "John Doe", "rank": "N/A" "email": ["john@company.com|mailto:"john@company.com]" "affiliation": "Other", "organization": "Company, Inc", "group-full": [ "adl-ousd/sql-lrs/Impact Level 2 Authorized", "/Impact Level 4 Authorized", "/Impact Level 5 Authorized" ], !Image preview.png|width=747,alt="Image preview.png"! ---- | F49: Scenario: Learner (Applicant) is completing the DSACCP application and needs to provide personal info, job info, learning history, etc. Given: data is in the ELRR When: The applicant opens the application Then: the applicant's information will be pre-populated by the system. Given: the applicant's data is NOT in the ELRR When: The applicant opens the application Then: the applicant's information will NOT be pre-populated (fields will be empty) by the system and can be entered manually MVP: allow applicant to edit information instead of requesting edits to parent system. | H49: 11523894 | I49: ERM-2865 | J49: Initiate Application | K49: To Do | L49: EDLM Portal | AF49: SAPRO
A50: Story | B50: ERM-3213 | C50: 11525758 | D50: As a [Learner], I want to access the latest D-SAACP Application for a new application. | E50: If I am a first time applicant we want to make sure learners DO NOT fill out the *2950-1 form.* This has created a lot of issues/need to redo things. The SARW-MS user interface should present the applicant with the current, correct version of the application form as indicated by persistent tags in the application footer. These tags will include info on: * Name of form (e.g, DD Form 2950 or DD Form 2950-1) * Form Version (e.g., FEB 2025) * Date of Update (e.g., Updated 02/05/2025) * Governing Policy (e.g., ‘Prescribed by DoDD 6495.03, DoDI 6495.03, and DTM 14-001’) ---- * Additionally, the application will be coded as fields in the UI. Applicants will be presented with the inital or refresher application questions/requirements appropriate to need. For new, the learner will select the type of application they are submitting (New Application or Renewal Application) and will select which position they are seeking certification for the following. # SAPR Program Administrator. # SAPR VA. # Principal SARC. # Supervisory SARC. # Collateral Duty SARC # Special Assignment SARC # Collateral Duty SAPR VA # Special Assignment SAPR VA Note: Here is the criteria that will indicate if the field should be greyed out or not. !image-20251212-152453.png|width=538,alt="image-20251212-152453.png"! # Additionally, they will have to ‘Please upload your certificate from your completed National Advocate Certification Program (NACP) pre-approved training course(s)’ ---- MVP = coding the application versions into the UI. FOC = consider a configurable UI based on form upload. [NOTE: this will include mapping all data fields to DLE fields / stnds] IMPLEMENTATION: All users will be presented an initial question that help determine whether or not they need to fill out a new or a renewal application. The question will ask them what type of application they are submitting. If they select new application, then they will be presented with a field to “Please upload your certificate from your completed D-SAACP pre-approved training courses” and a question to determine “which position are you seeking certification for”. If they select renewal application, they do not need to upload the D-SAACP training course certificate and will also be presented a question to determine “which position are you seeking certification for.” ---- MVP: hard coding and think about how we’re going to handle version changes going forward. | F50: Feature: Access latest D-SAACP Application for new application As a Learner, I want to access the latest D-SAACP Application So that I can begin a new application process. Scenario: Learner accesses the latest D-SAACP Application for a NEW application Given the Learner is logged into the system When the Learner navigates to the My application section Then the system should display a question asking what Application (new/renewal) they are submitting when the learner selects new, the system displays 2 additional items: 1. upload of the D-SAACP certificate; 2. which position are you seeking cert for. Scenario: Learner accesses the latest D-SAACP Application for a NEW application Given the Learner is logged into the system When the Learner navigates to the My application section Then the system should display a question asking what Application (new/renewal) they are submitting when the learner selects renewal, the system displays 1 additional items: 1 which position are you seeking cert for. And the application should be clearly labeled as the latest and correct version with the following fields: - Name of form (e.g, DD Form 2950 or DD Form 2950-1) - Form Version (e.g., FEB 2025) - Date of Update (e.g., Updated 02/05/2025) - Governing Policy (e.g., ‘Prescribed by DoDD 6495.03, DoDI 6495.03, and DTM 14-001’) | H50: 11523894 | I50: ERM-2865 | J50: Initiate Application | K50: In Progress | L50: EDLM Portal | AF50: SAPRO
A51: Story | B51: ERM-3212 | C51: 11525757 | D51: As a [Learner], I want to be able to be notified of any problems with my application so that I can fix it | E51: supervisors will comment on page as a whole OR on specific field(s) [feasibility for MVP?] and mark as needing applicant to change or not… templated comments or open comment fields? applicants are currently sent canned messages. Perhaps this is email notification that they need to contact XX. | F51: Scenario: Applicant has submitted an application Given: an error exists in an application When: a reviewer makes a comment on the application Then: a templated email is sent to the applicant's email address AND / or an alert is sent to the applicant's UI. (according to applicant's set preferences) Reviewer enters comment on learner application which triggers comment box specific email message / UI alert. -Comment box 1 --> box specific email message / notification [approved message TBD] -Comment box 2 --> box specific email message / notification [approved message TBD] -Comment box 3 --> box specific email message / notification [approved message TBD] Learner receives canned email message email message states: <insert approved message> email contains link to comment section within application [is this MVP?] Notification alert appears on Learner UI. Alert indicates <insert approved message> | H51: 11523898 | I51: ERM-2867 | J51: Monitor Application Intake and Validation | K51: Backlog | L51: EDLM Portal | AF51: SAPRO
A52: Business Requirement | B52: ERM-3211 | C52: 11525724 | D52: LDSS Graph Model Rebuild | E52: We need to condense our graph, so that not every property is its own node. We need to combine the UID, term, ID, Definition, into one term node Alias, org, and context are now their own nodes +*xBOM*+ UID: 0x000000000000000000000000000000001 ID: 0x000000000000000000000000000000001x000000000000000000000000000000001 Type: 1 CCVID: 0x0123456789ABCDE0123456789ABCDE01 Markup_Language: TBD Encoding: {UNICODE} Encoding_reference: https://www.unicode.org/versions/Unicode15.1.0/ Origination_Date: 01JAN1900 Currency_Date: 01JAN2025 CCV_Reference: {URL pointer to the current DoD CCV Repo} LCV_Reference: {URL pointer to the LCV Repo} Language: American English Common_Title: Day *Term* UID: 0x000000000000000000000000000000002 ID: 0x000000000000000000000000000000002x000000000000000000000000000000001 Definition: String of human readable text defining the term *Alias* Name: Human readable string (like bird) *Context* _UID: 0x000000000000000000000000000000002_ _ID: 0x000000000000000000000000000000002x000000000000000000000000000000001_ Name: Short string Description: Long string *LanguageSet* UID: 0x000000000000000000000000000000002 ID: 0x000000000000000000000000000000002x000000000000000000000000000000001 Name: Name of the language all associated terms belong to Description: Description of the language set (Optional) *Alias Term Pair* Name: The name of the pairing node Description: The description of when an alias is used for a term !image-20250926-134158.png|width=250,alt="image-20250926-134158.png"! | H52: 11516128 | I52: ERM-469 | J52: LDSS Functional Baseline | K52: Internal Grooming
A53: Story | B53: ERM-3210 | C53: 11525722 | D53: As a [Learner], I want to access the latest D-SAACP Application for a renewal application. | E53: If I am a first time applicant we want to make sure learners DO NOT fill out the *DD 2950 form.* This has created a lot of issues/need to redo things. The SARW-MS user interface should present the applicant with the current, correct version of the application form as indicated by persistent tags in the application footer. These tags will include info on: (Data source = Portal Backend) * Name of form (e.g, DD Form 2950 or DD Form 2950-1) * Form Version (e.g., FEB 2025) * Date of Update (e.g., Updated 02/05/2025) (if available) * Governing Policy (e.g., ‘Prescribed by DoDD 6495.03, DoDI 6495.03, and DTM 14-001’) Additionally, the application will be coded as fields in the UI. Applicants will be presented with the inital or refresher application questions/requirements appropriate to need. For renewal the learner will select the type of application they are submitting (New Application or Renewal Application) and will select which position they are seeking certification for the following. # SAPR Program Administrator. # SAPR VA. # Principal SARC. # Supervisory SARC. # Collateral Duty SARC # Special Assignment SARC # Collateral Duty SAPR VA # Special Assignment SAPR VA Note: Here is the criteria that will indicate if the field should be greyed out or not. !image-20251212-152453.png|width=538,alt="image-20251212-152453.png"! MVP = coding the application versions into the UI. FOC = consider a configurable UI based on form upload. [NOTE: this will include mapping all data fields to DLE fields / stnds] ---- IMPLEMENTATION: All users will be presented an initial question that help determine whether or not they need to fill out a new or a renewal application. The question will ask them what type of application they are submitting. If they select new application, then they will be presented with a field to “Please upload your certificate from your completed D-SAACP pre-approved training courses” and a question to determine “which position are you seeking certification for”. If they select renewal application, they do not need to upload the D-SAACP training course certificate and will also be presented a question to determine “which position are you seeking certification for.” ---- MVP: hard coding and think about how we’re going to handle version changes going forward. | F53: Feature: Access latest D-SAACP Application for renewal As a Learner, I want to access the latest D-SAACP Application So that I can complete my renewal application process. Scenario: Learner accesses the latest D-SAACP Application for a RENEWAL application Given: the Learner is logged into the system When: the Learner navigates to the My application section Then: the system should display a question asking what Application (new/renewal) they are submitting Then: the system should provide the latest version of the D-SAACP *Renewal* Application And the application should be clearly labeled as the latest and correct version with the following fields: - Name of form (e.g, DD Form 2950 or DD Form 2950-1) - Form Version (e.g., FEB 2025) - Date of Update (e.g., Updated 02/05/2025) - Governing Policy (e.g., ‘Prescribed by DoDD 6495.03, DoDI 6495.03, and DTM 14-001’) | H53: 11523894 | I53: ERM-2865 | J53: Initiate Application | K53: In Progress | L53: EDLM Portal | M53: elrr/elrr-services | AF53: SAPRO
A54: Business Requirement | B54: ERM-3209 | C54: 11525689 | D54: Creation of xAPI profile for load testing | E54: Generate an xAPI Profile JSON-LD document for use in DATASIM statement generation for SQL LRS load testing. | K54: Done
A55: Story | B55: ERM-3201 | C55: 11525578 | D55: ECCR CIS SD Elements | K55: In Progress
A56: Story | B56: ERM-3197 | C56: 11525571 | D56: ECCR CDS-UI SD Elements | K56: To Do
A57: Story | B57: ERM-3193 | C57: 11525564 | D57: ECCR CDS SD Elements | K57: Passed
A58: Story | B58: ERM-3186 | C58: 11525551 | D58: ECCR CMS-UI SD Elements | K58: To Do
A59: Story | B59: ERM-3185 | C59: 11525550 | D59: ECCR CMS SD Elements | K59: Closed
A60: Business Requirement | B60: ERM-3183 | C60: 11525450 | D60: VMET Transcript Format and Updates to External Services | E60: *VMET Ticket Grooming:* Use MMT sprint 29 to groom the VMET ticket in the current sprint, with work likely to begin in the next sprint due to current priorities. *Mapping and Format Creation:* The team will map existing system data into the new VMET transcript format, with Matt and Eric expected to collaborate on the technical implementation. | K60: Passed
A61: Business Requirement | B61: ERM-3180 | C61: 11525415 | D61: Import DSAACP Competency Framework into new ECCR | E61: Referenced linked work item for in-progress framework and import what we already have into rearchitected ECCR (understand it may not be fully completed right now). | K61: Backlog | L61: EDLM ECCR
A62: Story | B62: ERM-3179 | C62: 11525378 | D62: As a [DoD Service Member Advocate - Admin], I want to see transcript metrics, so I can monitor transcripts sent. | E62: Data that we have: * Demographics: ** First, Last name, current service branch, previous service branch (e.g., if they are a veteran), status (active duty, reserves, veteran…etc.), and rank of the individual sending the transcript. ** The Name, and location of the Academic Institution that the transcript was ‘Delivered’, ‘Viewed’, or ‘Downloaded’ to/by * # of Transcripts ‘Delivered’ to Academic Institutions and the date/time this occurred. * # of Transcripts ‘Viewed’ by Academic Institutions and the date/time this occurred. * # of Transcripts ‘Downloaded’ by Academic Institutions and the date/time this occurred. * # of Transcripts ‘Received’ by Academic Institutions and the date/time this occurred. * How many transcripts failed to be Delivered to Academic Institutions Example MVP Metrics we want to develop: * capture the data and be able to pull from the backend (logs?) ** total # transcripts sent. *** # and % sent by SMs *** # and % sent by Vets *** # and % sent to each Academic Institution *** # and % Sent by Branch ---- | F62: 1. The DOD Service Member Advocate - Admin shall be able to view transcript metrics related to transcripts sent to Academic Institutions. 2. The system shall capture and display the following data points: -Sender demographics: first name, last name, current service branch, previous service branch, status, and rank. -Academic Institution name and location where the transcript was Delivered, Viewed, Downloaded, or Received. -Count for each status: Opened, Delivered, Downloaded, and Pending. 3. The system shall provide summary metrics, including: -Total number of transcripts sent. -Number and percentage of transcripts sent by Service Members (SMs) and Veterans (Vets). -Number of transcripts sent to each Academic Institution. -Number of transcripts sent by Service Branch. 4. The system shall allow these metrics to be pulled from backend logs or a reporting dashboard. 5. All metrics shall be accurate, filterable, and time-stamped for reporting and monitoring purposes. 6. E2E tests are passing demoing this capability | H62: 11520580 | I62: ERM-1799 | J62: EDLM: Monitor Performance | K62: Backlog | AF62: MMT
A63: Story | B63: ERM-3171 | C63: 11525364 | D63: As a [Service Member Advocate], I want to see transcript metrics, so I can monitor transcripts sent. | K63: Prioritized
A64: Business Requirement | B64: ERM-3167 | C64: 11525326 | D64: Application Validation (workflow) - Decompose Requirements | E64: Begin decomposing Application Validation workflow Requirements | K64: Ready for Joint Grooming
A65: Business Requirement | B65: ERM-3166 | C65: 11525325 | D65: Cybersecurity Documentation (PIA & CTF) initiation (Nov 6 onward) | E65: Need to begin tracking this item. | K65: Closed
A66: Business Requirement | B66: ERM-3165 | C66: 11525324 | D66: Create System Architecture Report (SAR) Updates (Draft)​ and Database Design Document (DBDD) (Draft) | E66: Customer Deliverable, Brent and Audrey created drafts through confluence this ticket is to continue tracking the activity and share with customer in next call. | K66: Done
A67: Business Requirement | B67: ERM-3149 | C67: 11525052 | D67: Update and configure the EDLM portal for SAPRO, focusing on making key elements configurable for future customers and supporting initial SAPRO requirements. | E67: Configure and customize the EDLM portal for SAPRO, enabling dynamic branding, navigation, and content management to support SAPRO’s initial requirements and future scalability. --- *Description:* This ticket covers all necessary updates to transition the EDLM portal for SAPRO use, focusing on making key elements configurable for future customers and supporting SAPRO’s immediate needs. The work includes front-end and back-end changes, with an emphasis on admin-driven configuration and minimal hardcoding. --- *Scope of Work:* *Branding & Theming* * Replace DOT&E logo with SAPRO logo (enable configuration of logos, including favicon). * Update portal name to “SARW-MS Learning Portal” (enable configuration of Portal name). * MW note: In DOT&E, the tab name seems to vary between DOT&E and EDLM depending on what you have clicked on - we’ll need to fix this to be consistent * *Welcome Message* * Make the landing page welcome message configurable. * *Navigation Bar* * Make navigation bar elements configurable/hideable for future roles and permissions. * Prepare backend to support future role-based navigation restrictions. * *Onboarding Plans* * Remove or comment out onboarding plans section for now, as requirements are unclear and currently overlap with collections. * Retain code for future revival and configuration if needed. * *Collections* * Confirm public/private collection creation and visibility is admin-controlled. --- *Acceptance Criteria:* * SAPRO logo and portal name are updated and visible on the landing page. * Welcome message is editable by system admin via portal settings. * Navigation bar elements can be configured/hid by admin; homepage and search are always visible. * Spotlight courses are configurable; no hardcoded content. * Onboarding plans section is removed/commented out, with ability to restore when requirements are clear. * Collections navigation is configurable; public/private controls are admin-driven. * Metrics dashboard displays counts and percentages, with updated status labels and no timestamps. *Notes:* * This ticket is intended as a bulk configuration and customization task for SAPRO’s initial portal deployment. * All changes should be implemented to support future customer configurability and minimize hardcoding. * Revisit onboarding plans and DSACP requirements as new designs and feedback become available. | F67: 1. The EDLM portal shall be updated and configured for SAPRO with branding, navigation, and content adjustments. 2. The system shall allow dynamic branding, including updating the logo (SAPRO logo) and portal name (“SARW-MS Learning Portal”). 3. The welcome message on the landing page shall be configurable through the admin interface. 4. The navigation bar elements shall be configurable and hideable based on future roles and permissions. 5. The backend shall be prepared to support role-based navigation restrictions for future customers. 6. The Onboarding Plans section shall be temporarily removed or commented out, with the option to restore it later. 7. The Collections module shall ensure that public/private visibility and creation are admin-controlled. 8. Configuration changes shall be admin-driven with minimal hardcoding to enable scalability for future customers. | K67: Passed
A68: Business Requirement | B68: ERM-3145 | C68: 11525016 | D68: SAPRO_ Create Assessment Strategy Draft- Key Performance Indicators. | E68: *FROM PWS:* a) +_Assessment and Evaluation Strategy:_+ The ADL team will develop an overarching strategy for measuring and assessing the impacts of EDLM tools and technologies on DHRA / SAPRO end users. The strategy will provide an overall plan for documenting current processes and procedures and measuring the impacts of EDLM tools, technologies, and standards on workforce efficiency, productivity due to automation, and outcomes across each DHRA component’s mission area. A draft of the Assessment and Evaluation Strategy will be delivered NLT 3 months after funding has been received by the ADL vendor and will be updated quarterly with feedback from ADL, DHRA, and SAPRO stakeholders. *Deliverable:* Draft assessment and evaluation strategy due NLT 3 months after receipt of contractor funding. Document to be reviewed with government leadership and updated quarterly. Review documentation and determine details for this deliverable. *Key Performance Indicators and Assessment Strategies* The following KPIs have been identified by SAPRO: * *Optimize Time for Establishing New Accounts:* The solution shall optimize the time to create a new account and aim for a significant reduction in time for establishing a user account. * *Efficient D-SAACP Application Review Rate:* The solution shall measure the number of applications processed per unit of time, indicating the system's efficiency. * *Certification Verification Accuracy:* The solution shall measure the percentage of successfully verified certifications compared to the total number of verifications. * *Increase in Certification Compliance:* The solution shall measure the percentage of SARW with up-to-date certification before and after implementing D-SAACP modernization. * *Certification Renewal Compliance:* The solution shall measure the percentage of users who successfully renew their certifications on time, reflecting system efficiency. * *Continuing Education Tracking Accuracy:* The solution shall measure the system's accuracy in tracking and verifying continuing education requirements for certification renewal. * *Improved Response Time:* The solution shall measure the time it takes for the system to respond to user requests for certification processing and information retrieval. * *Reduction in Application Processing Time:* The solution shall evaluate the time it takes to process and verify D-SAACP applications and aim for a significant reduction. * *Certification Backlog:* The solution shall measure the number of pending certification or renewal applications, reflecting the system's ability to manage demand. * *System Availability:* The solution shall measure the percentage of time the database is operational and accessible, minimizing downtime. * *Enhanced Reporting:* The solution shall evaluate the quality and accessibility of reporting and analytics capabilities. * *Data Security Metrics:* The solution shall evaluate data security measures to protect sensitive information, with a focus on unauthorized access and data breaches. * *Data Accuracy and Integrity:* The solution shall measure the quality and accuracy of data within the database, including migrated data. * *Data Completeness:* The solution shall measure the percentage of data successfully migrated compared to the total dataset. This ensures that all relevant information has been transferred. * *Data Mapping Success:* The solution shall evaluate the success of the data mapping process by comparing the mapping documentation to the actual migrated data. Check if each field has been correctly mapped. | H68: 11523805 | I68: ERM-2800 | J68: Document Resolution | K68: Closed | L68: EDLM Portal
A69: Business Requirement | B69: ERM-3138 | C69: 11524937 | D69: Moodle Setup: Deploy a basic Moodle structure and a bare-bones Moodle, with retheming and organizational structure with block capabilities | K69: To Do | L69: EDLM Moodle LMS
A70: Business Requirement | B70: ERM-3133 | C70: 11524863 | D70: Review CG Example Data | K70: Backlog
A71: Business Requirement | B71: ERM-3128 | C71: 11524833 | D71: Build hi-fi wireframes for Application Intake | K71: Done
A72: Business Requirement | B72: ERM-3126 | C72: 11524831 | D72: Configure re-architected ECCR baseline with D-SAACP framework | E72: [DHRA shared requirements - 18 Sept 2025_ SAPRO Requirements.xlsx|https://adloffice365.sharepoint.com/:x:/s/EDLM_Extranet/Eai_lMCynEpJn6arzLnxQusBIdHqcrUvsgAOaGQG5C9Pag?e=PWU8r5] | K72: In Progress | L72: EDLM ECCR
A73: Business Requirement | B73: ERM-3125 | C73: 11524830 | D73: Portal Setup: Deploy a basic portal structure with retheming and organizational structure for SAPRO. | K73: To Do | L73: EDLM Portal
A74: Business Requirement | B74: ERM-3103 | C74: 11524757 | D74: Theming and logo update for DANTES Admin and Svc Member advocate | K74: Done
A75: Business Requirement | B75: ERM-3100 | C75: 11524723 | D75: Store goals in ELRR based on IDP inputs from learners | K75: Done
A76: Business Requirement | B76: ERM-3099 | C76: 11524722 | D76: Create "Leader" role for reports in EDLM Portal | K76: Passed
A77: Business Requirement | B77: ERM-3098 | C77: 11524695 | D77: The system will allow the IDP portal to map Learning Objectives (LOs) and goals to competency definitions so that employee development plans are aligned with organizational competency frameworks | E77: The portal must allow users to: * Select competencies from the ECCR framework. * Define goals that correspond to specific Knowledge, Skills, and Abilities (KSAs). * View KSA descriptions to guide goal formulation. * Track progress and update plans as competencies evolve. | F77: Users can browse and select competencies from the ECCR. Each competency includes a list of KSAs with descriptions. Users can create goals and associate them with selected KSAs. The system validates alignment between goals and competencies. Supervisors can review and comment on mapped goals. The portal supports reporting on competency alignment across IDPs. | K77: Done | L77: EDLM Portal
A78: Story | B78: ERM-3093 | C78: 11524558 | D78: As a [Competency Manager], I want to edit detailed information about competency or competency framework to include full description and metadata | E78: As a Competency Manager, I want to *edit* detailed information about a competency or competency framework so that *I can change* its properties, structure, and associations. This detailed view should include: * All properties defined in the SCD Implementation Guidance ([SCD Implementation Guidance.xlsx|https://adloffice365.sharepoint.com/:x:/s/RDE/ETaNjJzW9WVHtHxhlYPPZMwBCApOIeEIp8BoWEryesv3dg?e=hpDdRo]) tab “Properties by Class”, including, but not limited to: ** register an ID for the system to maintain it. The Competency ID should be easily accessible and copyable for reference or sharing. ** a Competency Statement that contextualizes and states what the learner can do ** a robust “type” that can be registered in the ECCR for future use. We expect “KSAT”, “Knowledge”, “Skill”, “Credential”, “Job”, etc. to be defined and referenced by many frameworks. * how frequently the competency or framework has been included in specific work roles, workforce elements, and career fields, in order to ** edit** how it is being used/applied across contexts. * I want the ability to take action from this view, such *as saving* the competency or framework to a personal collection or an existing framework I manage. * I want to edit the hierarchy of relationships, within the competency framework. For example, I want to see the parent competencies (which competencies use this in a hasPart, hasMember, or requires relationship) and be able to *edit* its associated children subcompetencies (which competencies this uses in a hasPart, hasMember, or requires relationship) * I want to do a mass edit in the competency framework by changing the hierarchies and relationships using the same UI used to originally build them. (added by Andy in Chat) | F78: Shweta: Please update the AC for this ticket. 10. There is E2E test verifying this functionality | H78: 11517807 | I78: ERM-1142 | J78: [ECCR] Create a Framework | K78: Ready for Joint Grooming | L78: eccr/cis | M78: eccr/cms | N78: EDLM ECCR | AF78: ECCR
A79: Business Requirement | B79: ERM-3089 | C79: 11524461 | D79: The ECCR UI shall have a portal for creating and managing framework profiles | E79: The ECCR shall have a portal that leverages the LDSS to to draft, publish, and manage ECCR Framework Profiles. MORE DATA NEEDED | K79: Backlog | L79: EDLM ECCR | M79: EDLM LDSS
A80: Business Requirement | B80: ERM-3088 | C80: 11524460 | D80: ADL - The LDSS Shall have an API that allows systems to publish draft node | K80: Backlog | L80: EDLM ECCR | M80: EDLM LDSS
A81: Business Requirement | B81: ERM-3087 | C81: 11524459 | D81: ECCR competency structure preservation | F81: 1. Hierarchal structure of parent child competencies shall be able to be copied preserving the original structure. 2. Hierarchal structure of parent child competencies shall be able to be arranged without affecting the original structure, creating an indepenent structure within the famework the competencies were linked too. 3. | K81: Backlog
A82: Business Requirement | B82: ERM-3065 | C82: 11524416 | D82: ADL- The LDSS Shall have an API that allows users to link items in the graph | K82: Backlog | L82: EDLM ECCR | M82: EDLM LDSS
A83: Business Requirement | B83: ERM-3064 | C83: 11524415 | D83: ADL - The LDSS shall include a an API endpoint that allows a system to CRUD language sets | K83: Backlog | L83: EDLM ECCR | M83: EDLM LDSS
A84: Business Requirement | B84: ERM-3062 | C84: 11524413 | D84: ECCR competency selection from another framework | E84: Competencies shall be selectable and integrable into another framework. To ensure conformity, the competencies shall initially be linked between the frameworks. This link shall be between the selected version of the competency and the new target framework. If there is a new version of the competency a depreciated tag will be attached to the competency version but not be automatically updated. | F84: 1. Competencies shall be able to be linked to other frameworks, appearing to the end use as though the competency has been copied to thier selected framework. 2. Competencies shall be linked to the version from a new framework. 3. Competencies shall be marked as depreciated if there is a newer version but not automatically updated. 4. E2E testing shall demonstrating adding competencies to a new framework and marking as depreciating. | K84: Backlog
A85: Business Requirement | B85: ERM-3061 | C85: 11524412 | D85: The ECCR shall have the ability so save a List Name for saved lists of competencies | E85: Once Validated, the list name shall be saved and able to be recalled later. The name shall be consistent wherever it appears. | F85: 1. List Name, when Saved will be consistent when its displayed 2. E2E testing shall be implemented to validate this. | K85: Backlog | L85: EDLM ECCR
A86: Business Requirement | B86: ERM-3059 | C86: 11524410 | D86: Competency Framework: Align the DSAACP competency framework to the standard | E86: * *Current:* * Gather the documented DSAACP competency framework from SharePoint or other shared locations. * Use ECCR deep dive sessions to demonstrate the data and plan for how the framework will be ingested and aligned with backend systems. * Link the framework documentation to this ticket * *Future:* * Review and extract relevant training materials from Nova and SAPRO tech to supplement the framework. * Manually input the competency framework data into the designated catalog system, ensuring all competencies, KSAs, and supporting materials are included. * Integrate available external catalogs (e.g., Coursera) as needed to enrich the competency mapping. | H86: 11521181 | I86: ERM-1899 | J86: [ECCR] Define Automated Mapping Criteria | K86: Done
A87: Business Requirement | B87: ERM-3058 | C87: 11524409 | D87: Catalog Inputs: Research and prepare catalog inputs, starting with Coursera and any available sample extracts | H87: 11523110 | I87: ERM-2645 | J87: [SAPRO] _ HCD Discovery | K87: Closed
A88: Business Requirement | B88: ERM-3056 | C88: 11524407 | D88: RTVM Development: Continue work on the RTVM, focusing on roles and permissions, and begin prioritizing requirements for SAPRO, DSAACP | H88: 11523110 | I88: ERM-2645 | J88: [SAPRO] _ HCD Discovery | K88: Done | L88: EDLM Portal
A89: Business Requirement | B89: ERM-3055 | C89: 11524406 | D89: Test MMT system usage, how well does the application handle the production load | E89: System usage testing ensures the MMT application can effectively support 2.5M active users and concurrency. Key metrics include system response time, concurrent user handling, resource utilization, and failure rates. Metrics: 1,000 users concurrently using Django; 1,000 and 5,000 hits per day (not concurrent) * Test Django applications to determine how many people can be using one instance and how we can scale it * May need to look into scalability within Platform One (understand how we are handling API calls and understand scaling and load balances in P1) * Determine need for optimization in the backend | K89: In Progress
A90: Business Requirement | B90: ERM-3054 | C90: 11524405 | D90: Test throughput for entry on learner record (areas include ELRR, and MMT consuming ELRR data) how long does it take for MMT to consume ~1M records | E90: Testing throughput analyzes the entire process from learner record entry to MMT consumption. We measure end-to-end latency, record ingestion rates, and timing variations using ELRR and MMT. MW notes - options discussed with James/Cliff on approach for getting data into P1: #1: Proxy to get around CNAP barrier #2: Handoff data and script to P1 *_#3 (approach we will be using and is similar to how we handled ELRR): Use JWT tp submit xAPI to SQL LRS; add widget to SQL LRS to enable batch-upload statement files_* | K90: In Progress
A91: Business Requirement | B91: ERM-3053 | C91: 11524404 | D91: The EDLM Portal will have an in-app talent manager notification capability | E91: Talent Manager * Due Dates * ERM-271 report delivered * [https://adlnet.atlassian.net/browse/ERM-308|https://adlnet.atlassian.net/browse/ERM-308|smart-link] report delivered * [https://adlnet.atlassian.net/browse/ERM-259|https://adlnet.atlassian.net/browse/ERM-259|smart-link] opened | F91: Talent Manager Notifications: 1.The system shall notify Talent Managers of upcoming due dates for tasks, reports, or evaluations. 2.Talent Managers shall receive a notification when a report has been successfully delivered. 3.The system shall notify individuals when they have been selected for consideration for a vacancy. | H91: 11515253 | I91: ERM-138 | J91: Portal: Baseline Functional Requirements | K91: Backlog | L91: EDLM Career Planning | M91: EDLM ECC | N91: EDLM ECCR | O91: EDLM ELRR | P91: EDLM Moodle LMS | Q91: EDLM Portal | R91: EDLM Talent Management | S91: elrr/elrr-external-services | T91: elrr/elrr-services | U91: mmt/mmt-portal
A92: Business Requirement | B92: ERM-3052 | C92: 11524403 | D92: The ECCR shall have the ability to validate a List Name for saved lists of comptencies | E92: The list name shall be validated on creation and when edited. The validation shall include a check to ensure that it is unique to the user account, this validation needs to run on both a creation and edit attempt. Additionally, validation shall include checks against none printing characters and other malicious characters. | F92: 1. Validation shall run before a new or edit list name is committed 2. Validation shall check for identical list names 3. Validation shall check for none printing and malicious characters 4. Unit tests and E2E tests shall validate functionality | K92: Backlog | L92: EDLM ECCR
A93: Business Requirement | B93: ERM-3051 | C93: 11524402 | D93: Competency Manager Interface | E93: The interface for Competency Managment shall be able to rearrange the competencies through a drag and drop system, visualize hierarchical and parent child relationships and require confirmation from the Competency Manager before any changes are made. The underlying schema that is locked or standardized shall not be able to be manipulated. A toggle button may be necessary to change between a hierarchical view and a parent child view. The drag and drop feature of the hierarchical and parent child view shall be active depending on which view is enabled. Changes made shall be confirmed by the Competency Manager through a confirmation screen. | F93: 1. Competency Management Interface shall display competencies in an interactive list manner. 2. Competency Management Interface shall be able to switch between a parent-child and hierarchy view. 3. Competency Management Interface shall ask confirmation from the Competency Manager before changes are made. 4. Competency Management Interface shall protect underlying schemes that have been locked or standardized from inadvertent and malicious manipulation. Schema's locked or standardized shall not be changed. 5. Competency Management Interface shall be capable of drag and drop rearrangement and manipulation of competencies. 6. E2E testing shall verify all functionality. | K93: Backlog | L93: eccr/cis | M93: eccr/cms | N93: EDLM ECCR
A94: Business Requirement | B94: ERM-3050 | C94: 11524401 | D94: Competency Parent-Child association manipulation method | E94: Competency Parent-Child relationships shall be able to be manipulated only when the both the parent and child competency share the same owner. This manipulation shall work in a manner similar to [https://adlnet.atlassian.net/browse/ERM-3047|https://adlnet.atlassian.net/browse/ERM-3047|smart-link] with a drag and drop method. | F94: 1. Competency parent child relationships shall be able to be manipulated in a fashion similar to hierarchal manipulation. 2. Parent child relationships shall only be able to be manipulated when the parent and child competency are both owned by the competency manager 3. E2E testing shall demonstrate the capabilities and verify functionality. | K94: Backlog | L94: eccr/cis | M94: eccr/cms | N94: EDLM ECCR
A95: Story | B95: ERM-3049 | C95: 11524398 | D95: As an [Academic Institution Registrar], when I add a user to the MMT Portal then the user should shall automatically notify assigned members via email once they have been added | E95: As an Academic Institution Registrar, I need the ability to assign multiple staff members to the Academic Institution MMT Portal. The system shall allow users with the correct permissions to add new users and assign them specific roles, ensuring appropriate access and responsibilities. Additionally, the MMT Portal shall automatically notify assigned members via email once they have been added. The MMT Portal will also provide verification directly in the system that a user has been successfully added. User Role management component is available. User Role management includes multiple levels of permissions with the ability to assign them to all staff members that I am assigned to. I can view all current settings, and edit them for each user. The interface will indicate success/failure of saving their permissions immediately after I have selected and saved them. Functionality will include: * Identify individuals (POCs) within the institution who can access or manage transcript-related permissions. * Enable permissions for downloading or receiving transcript notifications. | F95: 1. The Registrar shall be able to add new users to the Academic Institution’s MMT Portal. 2. The system shall allow the Registrar to assign roles and permissions to each user upon creation. 3. When a new user is successfully added, the system shall automatically send an email notification to the assigned members. 4. The system shall display a confirmation message verifying that the user has been successfully added. 5. The Registrar shall be able to view, edit, and manage permissions for all users within their institution. 6. The system shall indicate success or failure when saving updates to user roles or permissions. 7. Only users with appropriate permissions shall have access to manage user roles and transcript-related settings. 8. The system shall maintain a record of user additions and role assignments for audit purposes. 9. There is E2E test verifying this functionality. | H95: 11523039 | I95: ERM-2626 | J95: [MMT] Add/Remove Users | K95: Ready for Joint Grooming
A96: Story | B96: ERM-3048 | C96: 11524396 | D96: As an [Academic Institution Registrar], I want to delete multiple users to the MMT Portal | E96: As an Academic Institution Registrar, I need the ability to delete multiple staff members to the Academic Institution MMT Portal. The system shall allow users with the correct permissions to delete existing users. Note: The AI Registrar can select a specific record/s in the table/users to delete the user from the MMT Portal one at a time. By clicking on the delete button, it ensures that the user has been deleted/removed from the record/permissions. | F96: 1. The Registrar shall be able to select multiple users from the user list in the MMT Portal. 2. The system shall allow the Registrar to delete multiple selected users in a single action. 3. The system shall validate user permissions before allowing deletion. 4. A confirmation prompt shall appear before finalizing the delete action. 5. Once confirmed, the selected users shall be removed from the MMT Portal and their associated permissions revoked. 6. The system shall display a success message confirming that the users have been deleted. 7. The Registrar shall also have the option to delete a single user individually from the user list. 8. There is E2E test verifying this functionality | H96: 11523039 | I96: ERM-2626 | J96: [MMT] Add/Remove Users | K96: Ready for Joint Grooming
A97: Business Requirement | B97: ERM-3047 | C97: 11524392 | D97: Competency hierarchical relationship edit Method | E97: The hierarchy of competencies must be able to be manipulated and changed. The competencies hierarchy shall be manipulated through a drag and drop system where the competency can be made subordinate by dragging and dropping a competency on another competency. Competency hierarchy editing shall only be permitted to be performed when the Competency Manager owns all competencies in the target hierarchy. | F97: 1. Competencies hierarchy shall be changed by dragging and dropping them onto other competencies, making them a subordinate competency. 2. Competencies manipulation actions related to hierarchy shall be restricted based on ownership 3.E2E testing shall demonstrate the hierarchal manipulation of Competencies | K97: Backlog | L97: eccr/cis | M97: eccr/cms | N97: EDLM ECCR
A98: Business Requirement | B98: ERM-3046 | C98: 11524379 | D98: Edit Competency Method | E98: Competencies shall be editable using the form interface ([https://adlnet.atlassian.net/browse/ERM-3004|https://adlnet.atlassian.net/browse/ERM-3004|smart-link] ) editing shall be restricted to the competency owners. | F98: 1. Competencies shall be editable through the custom Framework and Competency Form 2. Edit of Competencies shall be restricted to the Competencies owners 3. E2E test shall validate that competencies are editable | K98: Backlog | L98: eccr/cis | M98: eccr/cms | N98: EDLM ECCR
A99: Story | B99: ERM-3036 | C99: 11524360 | D99: [SAPRO] _ IL2 Staging - Connected System of Systems - 90 Day Target | E99: Portal Requirements Discovery Develop Portal RTVM [DRAFT] DHRA Landing Page(s) SAPRO Landing Page | H99: 11523375 | I99: ERM-2690 | J99: [SAPRO] _ Initial SARW-MS Deployment and Configuration | K99: Internal Grooming | L99: EDLM Moodle LMS | M99: EDLM Portal | N99: moodle/moodle-lms | AF99: EDLM_UI/UX
A100: Business Requirement | B100: ERM-3035 | C100: 11524352 | D100: Remove Competency Method | E100: A method for removing competencies form frameworks shall be implemented. This shall be implemented using the selection feature from [https://adlnet.atlassian.net/browse/ERM-3015|https://adlnet.atlassian.net/browse/ERM-3015|smart-link]. This function shall only remove the competency from the framework, it will not be deleted. Orphaned Competencies shall be marked and tracked. The ability to remove competencies from a framework shall be reserved by the framework owners. | F100: 1. Individual competencies and bulk competencies are able to be removed from a framework. 2. Orphaned Competencies are handled in such a way that they are still retrievable. 3. Proper Access control for removal of competencies shall be present and implemented. 3. E2E testing will validate that competencies can be removed from frameworks both individually and in bulk. | K100: Backlog | L100: eccr/cis | M100: eccr/cms | N100: EDLM ECCR
...

Sheet UseCase to AcceptCriteria
A1: Hierarchy | E1: Title | F1: Space | G1: Releases (roll-up) | H1: Releases | I1: Team (roll-up) | J1: Team | K1: Assignee | L1: Reporter | M1: Sprint (roll-up) | N1: Sprint | O1: Target start date | P1: Target end date | Q1: Due date (roll-up) | R1: Due date | S1: Estimates (d) (roll-up) | T1: Estimates (d) | U1: Parent | V1: Priority | W1: Labels | X1: Components | Y1: Work item key | Z1: Work item status | AA1: Goal | AB1: Goal status | AC1: Idea | AD1: Progress (%) | AE1: Progress completed (d) | AF1: Progress remaining (d) | AG1: Progress (%) work item count (IC) | AH1: To do IC | AI1: In progress IC | AJ1: Done IC | AK1: Total IC | AL1: Start date (roll-up) | AM1: Start date | AN1: User Persona(s) | AO1: Description | AP1: Acceptance Criteria
A2: Use Case | E2: Configure: DLE System Management | F2: DLE - Top Level Planning | I2: ADL Human Centered Design [EXT] | J2: ADL Human Centered Design [EXT] | L2: Hunter Smith | M2: EDLM Sprint 47, EDLM Sprint 48 | Q2: 45910 | V2: Medium | Y2: DTLP-43 | Z2: Backlog | AD2: 0 | AE2: 0 | AF2: 0 | AG2: 0 | AH2: 3 | AI2: 0 | AJ2: 0 | AK2: 3 | AL2: 45882 | AO2: =IFERROR(VLOOKUP(Y2,'ERM project with Parent'!$B:$F,4,FALSE),"") | AP2: =IFERROR(VLOOKUP(Y2,'ERM project with Parent'!$B:$F,5,FALSE),"")
A3: Initiative | E3: Install & Configure DLE Systems | F3: DLE - Top Level Planning | I3: ADL Human Centered Design [EXT] | J3: ADL Human Centered Design [EXT] | L3: Hunter Smith | M3: EDLM Sprint 47, EDLM Sprint 48 | Q3: 45910 | U3: Configure: DLE System Management | V3: Medium | X3: EDLM Moodle LMS | Y3: DTLP-44 | Z3: Backlog | AD3: 0 | AE3: 0 | AF3: 0 | AG3: 0 | AH3: 6 | AI3: 0 | AJ3: 0 | AK3: 6 | AL3: 45882 | AO3: =IFERROR(VLOOKUP(Y3,'ERM project with Parent'!$B:$F,4,FALSE),"") | AP3: =IFERROR(VLOOKUP(Y3,'ERM project with Parent'!$B:$F,5,FALSE),"")
A4: Epic | E4: Provision Organizational Tenancies (Domains) | F4: EDLM - Requirements Management | J4: ADL Human Centered Design [EXT] | L4: Hunter Smith | U4: Install & Configure DLE Systems | V4: Medium | Y4: ERM-2093 | Z4: Backlog | AD4: 0 | AE4: 0 | AF4: 0 | AG4: 0 | AH4: 0 | AI4: 0 | AJ4: 0 | AK4: 0 | AO4: =IFERROR(VLOOKUP(Y4,'ERM project with Parent'!$B:$F,4,FALSE),"") -> 0 | AP4: =IFERROR(VLOOKUP(Y4,'ERM project with Parent'!$B:$F,5,FALSE),"") -> 0
A5: Epic | E5: Install TLA Reference Implementation Components | F5: EDLM - Requirements Management | J5: ADL Human Centered Design [EXT] | L5: Hunter Smith | U5: Install & Configure DLE Systems | V5: Medium | Y5: ERM-2094 | Z5: Backlog | AD5: 0 | AE5: 0 | AF5: 0 | AG5: 0 | AH5: 0 | AI5: 0 | AJ5: 0 | AK5: 0 | AO5: =IFERROR(VLOOKUP(Y5,'ERM project with Parent'!$B:$F,4,FALSE),"") -> 0 | AP5: =IFERROR(VLOOKUP(Y5,'ERM project with Parent'!$B:$F,5,FALSE),"") -> 0
A6: Epic | E6: Configure Software, Databases, and Services | F6: EDLM - Requirements Management | I6: ADL Human Centered Design [EXT] | J6: ADL Human Centered Design [EXT] | L6: Hunter Smith | U6: Install & Configure DLE Systems | V6: Medium | X6: EDLM Moodle LMS, EDLM Portal | Y6: ERM-2095 | Z6: Backlog | AD6: 0 | AE6: 0 | AF6: 0 | AG6: 33.33 | AH6: 4 | AI6: 0 | AJ6: 2 | AK6: 6 | AO6: =IFERROR(VLOOKUP(Y6,'ERM project with Parent'!$B:$F,4,FALSE),"") -> 0 | AP6: =IFERROR(VLOOKUP(Y6,'ERM project with Parent'!$B:$F,5,FALSE),"") -> 0
A7: Story | E7: As an [Administrator], I want to import multiple P2881 profiles into the ECC data model | F7: EDLM - Requirements Management | J7: ADL Human Centered Design [EXT] | L7: Hunter Smith | U7: Configure Software, Databases, and Services | V7: Medium | X7: ecc/ecc-openlxp-xis | Y7: ERM-2228 | Z7: Backlog | AD7: 0 | AE7: 0 | AF7: 0 | AG7: 0 | AH7: 0 | AI7: 0 | AJ7: 0 | AK7: 0 | AN7: EDLM Schema Administrator | AO7: =IFERROR(VLOOKUP(Y7,'ERM project with Parent'!$B:$F,4,FALSE),"") -> The source system (e.g., Coursera) needs to ingest *multiple* JSON schemas on profiles like webinars, newsletters, videos…etc. so the admin can push that information about the different course offerings out to the ECC and see the metadata in a more organized way in the XMS. NOTE: This entire process will occur via the XIS. Specifically, source system (e.g., Coursera) needs to connect their XIS as part of the XIA’s configuration then run the workflow, so the coursera courses get pulled into the XIS and the Admin can view the pulled metadata in the XMS. Previously, this process just pulled everything in one giant schema, which made it hard to manage the metadata because it was so much and so disorganized. | AP7: =IFERROR(VLOOKUP(Y7,'ERM project with Parent'!$B:$F,5,FALSE),"") -> 1. The Administrator shall be able to import multiple P2881 profile JSON schemas (e.g., webinars, newsletters, videos) into the ECC data model via XIS. 2. The source system (e.g., Coursera) must connect its XIS as part of the XIA configuration before the import workflow can be initiated. 3. The system shall allow the import of multiple distinct JSON schemas rather than a single aggregated schema. 4. Upon successful import, each profile type's metadata shall be parsed and organized according to the ECC data model. 5. The imported metadata shall be viewable by the Administrator in the XMS in a structured and categorized format. 6. The system shall validate the schema format of each profile before import and reject any non-compliant entries with an appropriate error message. 7. The workflow shall log success or failure messages for each profile imported to support traceability and debugging.
A8: Story | E8: As an [Experience Manager], I want to preview and sync course catalog page layouts with the structure of ingested content profiles | F8: EDLM - Requirements Management | J8: ADL Human Centered Design [EXT] | L8: Hunter Smith | U8: Configure Software, Databases, and Services | V8: Medium | X8: ldss/openlxp-xms | Y8: ERM-2229 | Z8: Backlog | AD8: 0 | AE8: 0 | AF8: 0 | AG8: 0 | AH8: 0 | AI8: 0 | AJ8: 0 | AK8: 0 | AN8: EDLM Experience Manager | AO8: =IFERROR(VLOOKUP(Y8,'ERM project with Parent'!$B:$F,4,FALSE),"") -> * In the XMS, when I am editing the data that is being pulled from source systems (e.g., Coursera) vis the XIA, I want to be able to see a preview of what the detailed course catalog page will look like for different types of profiles. For example, a ‘course’ detail page will have different data and layout than a ‘video’ or a ‘conference’ detail page in the course catalog. * In addition to seeing the data of each unique Profile, the XMS will also define how the data will be formatted in the ‘detailed’ page for each offering. i.e., the XMS will also push the formatting of what the catalog pages should look like. | AP8: =IFERROR(VLOOKUP(Y8,'ERM project with Parent'!$B:$F,5,FALSE),"") -> 1. The Experience Manager shall be able to preview the detailed course catalog page layout for each type of ingested content profile (e.g., course, video, conference) in the XMS. 2. The preview shall reflect both the structure and data fields specific to the selected profile type. 3. The XMS shall sync formatting rules and layout structure for each profile type to the catalog pages during ingestion via the XIA. 4. The preview shall update dynamically based on edits made to the content profile data within the XMS. 5. The layout and formatting defined in the XMS shall be accurately reflected on the corresponding course catalog page. 6. Each content type (course, video, conference) shall have a distinct layout template as configured in the XMS. 7. The Experience Manager shall be able to view and validate how mapped fields appear in the final catalog layout before publishing.
A9: Story | E9: As a [System Admin], I want access to help desk to customize the configuration of my DLE environment | F9: EDLM - Requirements Management | J9: ADL Human Centered Design [EXT] | L9: Ashley Howell | U9: Configure Software, Databases, and Services | V9: Medium | Y9: ERM-147 | Z9: Backlog | AD9: 0 | AE9: 0 | AF9: 0 | AG9: 0 | AH9: 0 | AI9: 0 | AJ9: 0 | AK9: 0 | AN9: EDLM IT System Administrator | AO9: =IFERROR(VLOOKUP(Y9,'ERM project with Parent'!$B:$F,4,FALSE),"") -> 0 | AP9: =IFERROR(VLOOKUP(Y9,'ERM project with Parent'!$B:$F,5,FALSE),"") -> 0
A10: Story | E10: As a [System Admin], I want to set up different course catalog spotlights for different DHRA customers within the EDLM Portal | F10: EDLM - Requirements Management | J10: ADL Human Centered Design [EXT] | U10: Configure Software, Databases, and Services | V10: Medium | X10: EDLM Portal | Y10: ERM-2701 | Z10: Backlog | AD10: 0 | AE10: 0 | AF10: 0 | AG10: 0 | AH10: 0 | AI10: 0 | AJ10: 0 | AK10: 0 | AO10: =IFERROR(VLOOKUP(Y10,'ERM project with Parent'!$B:$F,4,FALSE),"") -> 0 | AP10: =IFERROR(VLOOKUP(Y10,'ERM project with Parent'!$B:$F,5,FALSE),"") -> 0
A11: Epic | E11: Set up identity and access management | F11: EDLM - Requirements Management | I11: ADL Human Centered Design [EXT] | J11: ADL Human Centered Design [EXT] | L11: Hunter Smith | M11: EDLM Sprint 47, EDLM Sprint 48 | Q11: 45910 | U11: Install & Configure DLE Systems | V11: Medium | Y11: ERM-2713 | Z11: Backlog | AD11: 0 | AE11: 0 | AF11: 0 | AG11: 0 | AH11: 3 | AI11: 0 | AJ11: 0 | AK11: 3 | AL11: 45882 | AO11: =IFERROR(VLOOKUP(Y11,'ERM project with Parent'!$B:$F,4,FALSE),"") -> 0 | AP11: =IFERROR(VLOOKUP(Y11,'ERM project with Parent'!$B:$F,5,FALSE),"") -> 0
A12: Story | E12: As a [Site Admin] I would like to be able to configure the ECCR utilize JWT for user auth | F12: EDLM - Requirements Management | J12: ADL Human Centered Design [EXT] | L12: Hunter Smith | N12: EDLM Sprint 48 [EXT] [COMPLETED] + EDLM Sprint 47 [EXT] [COMPLETED] | U12: Set up identity and access management | V12: Medium | X12: eccr/frontend, eccr/backend | Y12: ERM-294 | Z12: Backlog | AD12: 0 | AE12: 0 | AF12: 0 | AG12: 0 | AH12: 0 | AI12: 0 | AJ12: 0 | AK12: 0 | AN12: EDLM IT System Administrator | AO12: =IFERROR(VLOOKUP(Y12,'ERM project with Parent'!$B:$F,4,FALSE),"") -> The ECCR Portal will leverage P1/Party Bus’s SSO and parse the JWT for required user information, like permissions and user name, email. JWT Information Includes: [https://p1docs.dso.mil/docs/party-bus/mission-devops-mdo/knowledge-base/keycloak-user-guides/jwt-integration/|https://p1docs.dso.mil/docs/party-bus/mission-devops-mdo/knowledge-base/keycloak-user-guides/jwt-integration/] Permissions Info: * affiliation: "Contractor" * group: (aka role) User Info: * organization: "Company, Inc." * name: "John Doe" * rank * preferred_username: "jdoe" * given_name: "John" * family_name: "Doe" * email: [john@company.com|mailto:"john@company.com] * activecac Status ** *Null* if no CAC ** *DoD ID* if CAC, for example: "DOE.JOHN.1234567890" | AP12: =IFERROR(VLOOKUP(Y12,'ERM project with Parent'!$B:$F,5,FALSE),"") -> 1. The ECCR portal shall authenticate users via JWT provided by P1/Party Bus SSO. 2. The system shall parse the JWT to extract user information, including: -affiliation -group (role) -organization -name, given_name, family_name -preferred_username -email -rank -active cac status (null if no CAC; DoD ID if present) 3. The extracted user data shall be used to assign permissions and personalize the user experience. 4. JWT parsing and configuration shall be manageable by the Site Admin.
A13: Story | E13: As a [Competency Manager], I want my credentials (e.g., name) to be populated when I log in so that I can easily confirm that I am accessing my account. | F13: EDLM - Requirements Management | J13: ADL Human Centered Design [EXT] | L13: Ashley Howell | U13: Set up identity and access management | V13: Medium | Y13: ERM-350 | Z13: Backlog | AD13: 0 | AE13: 0 | AF13: 0 | AG13: 0 | AH13: 0 | AI13: 0 | AJ13: 0 | AK13: 0 | AN13: EDLM Competency Manager | AO13: =IFERROR(VLOOKUP(Y13,'ERM project with Parent'!$B:$F,4,FALSE),"") -> Competency Manager | AP13: =IFERROR(VLOOKUP(Y13,'ERM project with Parent'!$B:$F,5,FALSE),"") -> 0
A14: Story | E14: As a Competency Manager, I want my credentials (e.g., name) to be populated when I log in so that I can easily confirm that I am accessing my account. | F14: EDLM - Requirements Management | J14: ADL Human Centered Design [EXT] | U14: Set up identity and access management | V14: Medium | Y14: ERM-1554 | Z14: Backlog | AD14: 0 | AE14: 0 | AF14: 0 | AG14: 0 | AH14: 0 | AI14: 0 | AJ14: 0 | AK14: 0 | AO14: =IFERROR(VLOOKUP(Y14,'ERM project with Parent'!$B:$F,4,FALSE),"") -> 0 | AP14: =IFERROR(VLOOKUP(Y14,'ERM project with Parent'!$B:$F,5,FALSE),"") -> 0
A15: Epic | E15: Integrate with existing DoD Infrastructure | F15: EDLM - Requirements Management | J15: ADL Human Centered Design [EXT] | L15: Hunter Smith | U15: Install & Configure DLE Systems | V15: Medium | X15: EDLM Portal | Y15: ERM-2714 | Z15: Backlog | AD15: 0 | AE15: 0 | AF15: 0 | AG15: 0 | AH15: 1 | AI15: 0 | AJ15: 0 | AK15: 1 | AN15: EDLM IT System Admin | AO15: =IFERROR(VLOOKUP(Y15,'ERM project with Parent'!$B:$F,4,FALSE),"") -> 0 | AP15: =IFERROR(VLOOKUP(Y15,'ERM project with Parent'!$B:$F,5,FALSE),"") -> 0
A16: Story | E16: As an [ADL Admin], I want to configure Zendesk so I can integrate the defined business rules and workflows | F16: EDLM - Requirements Management | K16: Desiree Esiere | U16: Integrate with existing DoD Infrastructure | V16: High | W16: Zendesk_DANTES | X16: EDLM Portal | Y16: ERM-2832 | Z16: Backlog | AD16: 0 | AE16: 0 | AF16: 0 | AG16: 0 | AH16: 0 | AI16: 0 | AJ16: 0 | AK16: 0 | AN16: EDLM IT System Admin | AO16: =IFERROR(VLOOKUP(Y16,'ERM project with Parent'!$B:$F,4,FALSE),"") -> 0 | AP16: =IFERROR(VLOOKUP(Y16,'ERM project with Parent'!$B:$F,5,FALSE),"") -> 0
A17: Epic | E17: Validate System Readiness | F17: EDLM - Requirements Management | J17: ADL Human Centered Design [EXT] | L17: Hunter Smith | U17: Install & Configure DLE Systems | V17: Medium | Y17: ERM-2715 | Z17: Backlog | AD17: 0 | AE17: 0 | AF17: 0 | AG17: 0 | AH17: 0 | AI17: 0 | AJ17: 0 | AK17: 0 | AO17: =IFERROR(VLOOKUP(Y17,'ERM project with Parent'!$B:$F,4,FALSE),"") -> 0 | AP17: =IFERROR(VLOOKUP(Y17,'ERM project with Parent'!$B:$F,5,FALSE),"") -> 0
A18: Initiative | E18: Maintenance: Cybersecurity / Patches / Updates | F18: DLE - Top Level Planning | J18: ADL Human Centered Design [EXT] | L18: Hunter Smith | U18: Configure: DLE System Management | V18: Medium | Y18: DTLP-45 | Z18: Backlog | AD18: 0 | AE18: 0 | AF18: 0 | AG18: 0 | AH18: 0 | AI18: 0 | AJ18: 0 | AK18: 0 | AO18: =IFERROR(VLOOKUP(Y18,'ERM project with Parent'!$B:$F,4,FALSE),"") | AP18: =IFERROR(VLOOKUP(Y18,'ERM project with Parent'!$B:$F,5,FALSE),"")
A19: Initiative | E19: Help Desk & Support | F19: DLE - Top Level Planning | J19: ADL Human Centered Design [EXT] | L19: Hunter Smith | U19: Configure: DLE System Management | V19: Medium | Y19: DTLP-46 | Z19: Backlog | AD19: 0 | AE19: 0 | AF19: 0 | AG19: 0 | AH19: 0 | AI19: 0 | AJ19: 0 | AK19: 0 | AO19: =IFERROR(VLOOKUP(Y19,'ERM project with Parent'!$B:$F,4,FALSE),"") | AP19: =IFERROR(VLOOKUP(Y19,'ERM project with Parent'!$B:$F,5,FALSE),"")
A20: Use Case | E20: Configure: TLA Data Management | F20: DLE - Top Level Planning | I20: ADL RD&E [EXT], ADL Human Centered Design [EXT], Deloitte [EXT] | J20: ADL Human Centered Design [EXT] | L20: Hunter Smith | V20: Medium | Y20: DTLP-38 | Z20: Backlog | AD20: 0 | AE20: 0 | AF20: 0 | AG20: 0 | AH20: 4 | AI20: 0 | AJ20: 0 | AK20: 4 | AO20: =IFERROR(VLOOKUP(Y20,'ERM project with Parent'!$B:$F,4,FALSE),"") | AP20: =IFERROR(VLOOKUP(Y20,'ERM project with Parent'!$B:$F,5,FALSE),"")
A21: Initiative | E21: Manage a Language Set | F21: DLE - Top Level Planning | I21: ADL RD&E [EXT], ADL Human Centered Design [EXT], Deloitte [EXT] | J21: ADL Human Centered Design [EXT] | L21: Hunter Smith | U21: Configure: TLA Data Management | V21: Medium | X21: EDLM LDSS | Y21: DTLP-39 | Z21: Backlog | AD21: 0 | AE21: 0 | AF21: 0 | AG21: 0 | AH21: 4 | AI21: 0 | AJ21: 0 | AK21: 4 | AO21: =IFERROR(VLOOKUP(Y21,'ERM project with Parent'!$B:$F,4,FALSE),"") | AP21: =IFERROR(VLOOKUP(Y21,'ERM project with Parent'!$B:$F,5,FALSE),"")
A22: Epic | E22: [LDSS] Configure Language Set | F22: EDLM - Requirements Management | L22: Hunter Smith | U22: Manage a Language Set | V22: Medium | X22: EDLM LDSS | Y22: ERM-2098 | Z22: Backlog | AD22: 0 | AE22: 0 | AF22: 0 | AG22: 0 | AH22: 0 | AI22: 0 | AJ22: 0 | AK22: 0 | AO22: =IFERROR(VLOOKUP(Y22,'ERM project with Parent'!$B:$F,4,FALSE),"") -> 0 | AP22: =IFERROR(VLOOKUP(Y22,'ERM project with Parent'!$B:$F,5,FALSE),"") -> 0
A23: Epic | E23: [LDSS] Create a Language Set | F23: EDLM - Requirements Management | I23: ADL RD&E [EXT], ADL Human Centered Design [EXT], Deloitte [EXT] | J23: ADL Human Centered Design [EXT] | K23: Andy Johnson | L23: Hunter Smith | U23: Manage a Language Set | V23: Medium | X23: EDLM LDSS, P2881 Learning Experience Metadata | Y23: ERM-2099 | Z23: Backlog | AD23: 0 | AE23: 0 | AF23: 0 | AG23: 9.09 | AH23: 20 | AI23: 0 | AJ23: 2 | AK23: 22 | AO23: =IFERROR(VLOOKUP(Y23,'ERM project with Parent'!$B:$F,4,FALSE),"") -> 0 | AP23: =IFERROR(VLOOKUP(Y23,'ERM project with Parent'!$B:$F,5,FALSE),"") -> 0
A24: Story | E24: As a [Glossary Manager], when Indexing a LanguageSet, I would like to upload a LanguageSets file to index the terms and definitions it contains | F24: EDLM - Requirements Management | J24: ADL Human Centered Design [EXT] | L24: Hunter Smith | U24: [LDSS] Create a Language Set | V24: Medium | X24: EDLM LDSS, ldss/openlxp-xss, ldss-xss/CCV-LCV, ldss/openlxp-xss-ui | Y24: ERM-462 | Z24: Backlog | AD24: 0 | AE24: 0 | AF24: 0 | AG24: 0 | AH24: 0 | AI24: 0 | AJ24: 0 | AK24: 0 | AN24: EDLM Glossary Manager | AO24: =IFERROR(VLOOKUP(Y24,'ERM project with Parent'!$B:$F,4,FALSE),"") -> I need to upload a file (*CSV*) that contains information about all of my terms. This will form a new LCV. Here is the example language Set that Hunter has: !Language Set.png|width=756,height=540,alt="Language Set.png"! draft wireframe design: !image-20240926-011821.png|width=1282,height=732,alt="image-20240926-011821.png"! NOTE: export filetypes = XML, JSON | AP24: =IFERROR(VLOOKUP(Y24,'ERM project with Parent'!$B:$F,5,FALSE),"") -> 1. File Upload: The Glossary Manager must be able to upload a CSV file containing a set of terms and their definitions to create a new LanguageSet for indexing. 2. File Validation: The system should validate the uploaded CSV file to ensure it contains the required structure (terms and definitions) before indexing. 3. Indexing Confirmation: Upon successful upload and validation, the system should confirm the indexing process for the LanguageSet is initiated. 4. Export Options: The Glossary Manager should be able to export the indexed LanguageSet in XML and JSON formats. 5. Error Handling: If the CSV file contains incorrect data or formatting, the system should notify the user with an error message and provide guidance on correcting the file.
A25: Story | E25: As a [Glossary Manager] I would like to save my LanguageSet as a draft to resume later | F25: EDLM - Requirements Management | J25: ADL Human Centered Design [EXT] | L25: Hunter Smith | U25: [LDSS] Create a Language Set | V25: Medium | X25: EDLM LDSS, ldss/openlxp-xss, ldss-xss/CCV-LCV, ldss/openlxp-xss-ui | Y25: ERM-514 | Z25: Backlog | AD25: 0 | AE25: 0 | AF25: 0 | AG25: 0 | AH25: 0 | AI25: 0 | AJ25: 0 | AK25: 0 | AN25: EDLM Glossary Manager | AO25: =IFERROR(VLOOKUP(Y25,'ERM project with Parent'!$B:$F,4,FALSE),"") -> If I am making changes to my LCV I need to be able to come back to it. This means that once I upload my file, I need to be able to edit the ‘terms’ within it. I might need to edit some of the metadata, link to another term’s definition, and/or see all of the aligned definitions for other terms to my term. more info on the process: Building your own Local Controlled Vocabulary (LCV) is a straightforward process designed to help you tailor terminology to your organization’s needs while maintaining alignment with authoritative standards (i.e., CCVs). * *Upload Schema File:* To begin, you can upload a schema file containing your desired aliases, terms, contexts, context descriptions, and definitions. Simply prepare a structured file (like CSV or XML) and use the upload feature in the LCV interface to import it. This will automatically extract the relevant fields into your LCV. * *Deconfliction:* Next, the deconfliction process helps you identify potential overlaps in terminology. When you upload a new schema file, you’ll see deconfliction results that display various definitions along with a percentage indicating how closely they match definitions for your terms. ** If you find that a definition corresponds to the definition you want to use for one of your terms, you can map the term to that definition and treat it as a different alias. In this case, you will need to create a new Alias, Tag, and/or Label, as these represent the vernacular and the context in which they are used. This grouping is essential for understanding how local terminology relates to authoritative definitions. * *Copy Existing Aliases:* If you already have established aliases, you can easily incorporate them into your LCV by selecting an existing alias from the glossary. Copying an alias will duplicate key fields such as the UID, Term, Context, Context Description, and Definition. These fields are not editable because they are governed by a governance authority, ensuring consistency and integrity across the vocabulary. ** *Customize Fields:* However, you can edit the Alias, Tag, and Label fields to customize the term for local usage. This flexibility allows you to create a user-friendly vocabulary that resonates with your team while ensuring proper mapping to the Canonical Controlled Vocabulary (CCV). *SAVE AT ANY PART OF THE PROCESS [is this a manual save; consider auto save from a user experience - RESEARCH]* * transparency of save | AP25: =IFERROR(VLOOKUP(Y25,'ERM project with Parent'!$B:$F,5,FALSE),"") -> 1. Draft Saving: The Glossary Manager must be able to save their LanguageSet as a draft at any point during the process, allowing them to return and continue editing at a later time. 2. Term Editing: After uploading a schema file, the Glossary Manager can edit the terms within the LanguageSet, including metadata adjustments, linking terms to other definitions, and viewing aligned definitions. 3. Deconfliction Results: Upon uploading the schema file, the Glossary Manager will see deconfliction results showing matching definitions with percentage indicators for comparison. 4. Alias Customization: The Glossary Manager must be able to create new Aliases, Tags, and Labels when mapping a term to a definition, and edit these fields to reflect local usage. 5. Existing Aliases: The Glossary Manager can copy existing aliases from the glossary, but core fields such as UID, Term, Context, and Definition will remain non-editable to maintain governance authority. 6. Draft Resumption: The Glossary Manager can resume working on a saved draft of the LanguageSet, with all previous changes intact, including term edits and metadata updates.
A26: Story | E26: As a [Glossary Manager] I would like to fully define term definitions | F26: EDLM - Requirements Management | J26: ADL Human Centered Design [EXT] | L26: Florian Tolk | U26: [LDSS] Create a Language Set | V26: Medium | X26: EDLM LDSS, ldss/openlxp-xss, ldss-xss/CCV-LCV, ldss/openlxp-xss-ui | Y26: ERM-470 | Z26: Backlog | AD26: 0 | AE26: 0 | AF26: 0 | AG26: 0 | AH26: 0 | AI26: 0 | AJ26: 0 | AK26: 0 | AN26: EDLM Glossary Manager | AO26: =IFERROR(VLOOKUP(Y26,'ERM project with Parent'!$B:$F,4,FALSE),"") -> An entry for a term will have (at least) these fields (not sure if there will be more fields than this). some fields are or are not editable. (see photo of draft wireframe) the UID, Term, Context, Context Description, and Definition fields are not editable because they are governed by a governance authority, ensuring consistency and integrity across the vocabulary. However, you can edit the Alias, Tag, and Label fields to customize the term for local usage. !image-20240926-012539.png|width=1145,height=552,alt="image-20240926-012539.png"! | AP26: =IFERROR(VLOOKUP(Y26,'ERM project with Parent'!$B:$F,5,FALSE),"") -> As a Glossary Manager, I want to fully define term definitions with the following conditions: The term entry must include the following fields: UID Term Context Context Description Definition Alias (Editable) Tag (Editable) Label (Editable) The following fields are not editable due to governance authority rules: UID Term Context Context Description Definition The Alias, Tag, and Label fields must be editable to allow customization for local usage. Terms and Termsets shall be flaggable as Draft for further editing and review
A27: Story | E27: As a [Glossary Manager], when Registering Terms, I would like the ability to input a definition for a Term (CCVID) | F27: EDLM - Requirements Management | J27: ADL Human Centered Design [EXT] | L27: Hunter Smith | U27: [LDSS] Create a Language Set | V27: Medium | X27: EDLM LDSS, ldss/openlxp-xss, ldss-xss/CCV-LCV, ldss/openlxp-xss-ui | Y27: ERM-497 | Z27: Backlog | AD27: 0 | AE27: 0 | AF27: 0 | AG27: 0 | AH27: 0 | AI27: 0 | AJ27: 0 | AK27: 0 | AN27: EDLM Glossary Manager | AO27: =IFERROR(VLOOKUP(Y27,'ERM project with Parent'!$B:$F,4,FALSE),"") -> [~accountid:70121:f7a2f8d0-f750-4b60-8e7b-fb1de0d18b82] Need to discuss? when we were talking with jordan he mentioned: the UID, Term, Context, Context Description, and {color:#bf2600}Definition {color}fields are not editable because they are governed by a governance authority, ensuring consistency and integrity across the vocabulary. ______ An entry for a term will have (at least) these fields (not sure if there will be more fields than this). some fields are or are not editable. (see photo of draft wireframe) the UID, Term, Context, Context Description, and Definition fields are not editable because they are governed by a governance authority, ensuring consistency and integrity across the vocabulary. However, you can edit the Alias, Tag, and Label fields to customize the term for local usage. !image-20240926-012539.png|width=1145,height=552,alt="image-20240926-012539.png"! | AP27: =IFERROR(VLOOKUP(Y27,'ERM project with Parent'!$B:$F,5,FALSE),"") -> 1. The system shall display the following non-editable fields when registering a term: UID Term Context Context Description Definition These fields are governed by a governance authority and cannot be modified to maintain consistency and integrity. 2. The system shall allow the Glossary Manager to input and edit the following fields for customization: Alias Tag Label 3. The system shall ensure that any non-editable fields remain locked from user modification during the term registration process. 4. The term registration process shall be considered complete only when all required fields (editable and non-editable) are populated.
A28: Story | E28: As a [Glossary Manager], when Registering Terms, i would like to capture Context, Context Description, and Labels for a Term (CCVID) | F28: EDLM - Requirements Management | J28: ADL Human Centered Design [EXT] | L28: Hunter Smith | U28: [LDSS] Create a Language Set | V28: Medium | X28: EDLM LDSS, ldss/openlxp-xss, ldss-xss/CCV-LCV, ldss/openlxp-xss-ui | Y28: ERM-1033 | Z28: Backlog | AD28: 0 | AE28: 0 | AF28: 0 | AG28: 0 | AH28: 0 | AI28: 0 | AJ28: 0 | AK28: 0 | AN28: EDLM Glossary Manager | AO28: =IFERROR(VLOOKUP(Y28,'ERM project with Parent'!$B:$F,4,FALSE),"") -> 0 | AP28: =IFERROR(VLOOKUP(Y28,'ERM project with Parent'!$B:$F,5,FALSE),"") -> 1. The system shall display the following non-editable fields when registering a term: UID Term Context Context Description Definition 2. These fields shall be governed by a governance authority and cannot be modified to ensure consistency and integrity of the glossary data. 3. The Glossary Manager shall have the ability to capture and input labels associated with the term during the registration process. 4. The system shall provide a clear distinction between editable and non-editable fields to avoid confusion during term registration.
A29: Story | E29: As a [Glossary Manager] when Registering Terms, I would like there to be a deconfliction service that notifies me if my desired definition already exists and point me to the correct term within that language set | F29: EDLM - Requirements Management | J29: ADL Human Centered Design [EXT] | L29: Hunter Smith | U29: [LDSS] Create a Language Set | V29: Medium | X29: EDLM LDSS, ldss/openlxp-xss, ldss-xss/CCV-LCV, ldss/openlxp-xss-ui | Y29: ERM-498 | Z29: Backlog | AD29: 0 | AE29: 0 | AF29: 0 | AG29: 0 | AH29: 0 | AI29: 0 | AJ29: 0 | AK29: 0 | AN29: EDLM Glossary Manager | AO29: =IFERROR(VLOOKUP(Y29,'ERM project with Parent'!$B:$F,4,FALSE),"") -> * If the definition is moderately atomic (one meaning & concept) * If a substantively equivalent definition exists * If a potential conflict or deviation may exist due to submission * Generate a conflict/deviation notification with indicators draft wireframe: !image-20240926-012325.png|width=1227,height=863,alt="image-20240926-012325.png"! more info on the process: Building your own Local Controlled Vocabulary (LCV) is a straightforward process designed to help you tailor terminology to your organization’s needs while maintaining alignment with authoritative standards (i.e., CCVs). * *Upload Schema File:* To begin, you can upload a schema file containing your desired aliases, terms, contexts, context descriptions, and definitions. Simply prepare a structured file (like CSV or XML) and use the upload feature in the LCV interface to import it. This will automatically extract the relevant fields into your LCV. * *Deconfliction:* Next, the deconfliction process helps you identify potential overlaps in terminology. When you upload a new schema file, you’ll see deconfliction results that display various definitions along with a percentage indicating how closely they match definitions for your terms. ** If you find that a definition corresponds to the definition you want to use for one of your terms, you can map the term to that definition and treat it as a different alias. In this case, you will need to create a new Alias, Tag, and/or Label, as these represent the vernacular and the context in which they are used. This grouping is essential for understanding how local terminology relates to authoritative definitions. | AP29: =IFERROR(VLOOKUP(Y29,'ERM project with Parent'!$B:$F,5,FALSE),"") -> 1. As a Glossary Manager, when registering a term, the system shall notify me if the submitted definition is moderately atomic (i.e., represents one distinct meaning or concept) and already exists in the glossary. 2. If a substantively equivalent definition is identified in the system, a notification shall be generated pointing me to the correct term and its existing definition. 3. The system shall generate a conflict or deviation notification if the submitted definition potentially conflicts with or deviates from an existing term. 4. Conflict/deviation notifications shall include clear indicators highlighting the nature of the conflict and provide suggestions for resolving it.
